<?xml version="1.0" encoding="UTF-8"?>
<!DOCTYPE score-partwise PUBLIC "-//Recordare//DTD MusicXML 3.0 Partwise//EN" "http://www.musicxml.org/dtds/partwise.dtd">
<score-partwise>
  <work>
    <work-title>Alma Redemptoris Mater</work-title>
    </work>
  <identification>
    <creator type="composer">Anonymous</creator>
    <encoding>
      <software>MuseScore 2.0.2</software>
      <encoding-date>2016-02-16</encoding-date>
      <supports element="accidental" type="yes"/>
      <supports element="beam" type="yes"/>
      <supports element="print" attribute="new-page" type="yes" value="yes"/>
      <supports element="print" attribute="new-system" type="yes" value="yes"/>
      <supports element="stem" type="yes"/>
      </encoding>
    </identification>
  <defaults>
    <scaling>
      <millimeters>7.05556</millimeters>
      <tenths>40</tenths>
      </scaling>
    <page-layout>
      <page-height>1584</page-height>
      <page-width>1224</page-width>
      <page-margins type="even">
        <left-margin>56.6929</left-margin>
        <right-margin>56.6929</right-margin>
        <top-margin>56.6929</top-margin>
        <bottom-margin>113.386</bottom-margin>
        </page-margins>
      <page-margins type="odd">
        <left-margin>56.6929</left-margin>
        <right-margin>56.6929</right-margin>
        <top-margin>56.6929</top-margin>
        <bottom-margin>113.386</bottom-margin>
        </page-margins>
      </page-layout>
    <word-font font-family="FreeSerif" font-size="10"/>
    <lyric-font font-family="FreeSerif" font-size="11"/>
    </defaults>
  <credit page="1">
    <credit-words default-x="612" default-y="1527.31" justify="center" valign="top" font-size="24">Alma redemptoris mater 2</credit-words>
    </credit>
  <credit page="1">
    <credit-words default-x="1167.31" default-y="1427.31" justify="right" valign="bottom" font-size="12">Anonymous</credit-words>
    </credit>
  <part-list>
    <score-part id="P1">
      <part-name>Piano</part-name>
      <part-abbreviation>Pno.</part-abbreviation>
      <score-instrument id="P1-I1">
        <instrument-name>Piano</instrument-name>
        </score-instrument>
      <midi-device id="P1-I1" port="1"></midi-device>
      <midi-instrument id="P1-I1">
        <midi-channel>1</midi-channel>
        <midi-program>1</midi-program>
        <volume>78.7402</volume>
        <pan>0</pan>
        </midi-instrument>
      </score-part>
    </part-list>
  <part id="P1">
    <measure number="1" width="1110.61">
      <print>
        <system-layout>
          <system-margins>
            <left-margin>0.00</left-margin>
            <right-margin>0.00</right-margin>
            </system-margins>
          <top-system-distance>170.00</top-system-distance>
          </system-layout>
        </print>
      <attributes>
        <divisions>1</divisions>
        <key>
          <fifths>-1</fifths>
          </key>
        <time>
          <beats>63</beats>
          <beat-type>4</beat-type>
          </time>
        <clef>
          <sign>G</sign>
          <line>2</line>
          <clef-octave-change>-1</clef-octave-change>
          </clef>
        </attributes>
      <note default-x="97.06" default-y="-35.00">
        <pitch>
          <step>F</step>
          <octave>3</octave>
          </pitch>
        <duration>1</duration>
        <voice>1</voice>
        <type>quarter</type>
        <stem>none</stem>
        <notations>
          <slur type="start" number="1"/>
          </notations>
        <lyric number="1">
          <syllabic>begin</syllabic>
          <text>Al</text>
          </lyric>
        </note>
      <note default-x="124.07" default-y="-25.00">
        <pitch>
          <step>A</step>
          <octave>3</octave>
          </pitch>
        <duration>1</duration>
        <voice>1</voice>
        <type>quarter</type>
        <stem>none</stem>
        </note>
      <note default-x="151.07" default-y="-20.00">
        <pitch>
          <step>B</step>
          <alter>-1</alter>
          <octave>3</octave>
          </pitch>
        <duration>1</duration>
        <voice>1</voice>
        <type>quarter</type>
        <stem>none</stem>
        </note>
      <note default-x="178.08" default-y="-15.00">
        <pitch>
          <step>C</step>
          <octave>4</octave>
          </pitch>
        <duration>1</duration>
        <voice>1</voice>
        <type>quarter</type>
        <stem>none</stem>
        <notations>
          <slur type="stop" number="1"/>
          </notations>
        </note>
      <note default-x="205.08" default-y="-10.00">
        <pitch>
          <step>D</step>
          <octave>4</octave>
          </pitch>
        <duration>1</duration>
        <voice>1</voice>
        <type>quarter</type>
        <stem>none</stem>
        <notations>
          <slur type="start" number="1"/>
          </notations>
        </note>
      <note default-x="232.09" default-y="-5.00">
        <pitch>
          <step>E</step>
          <octave>4</octave>
          </pitch>
        <duration>1</duration>
        <voice>1</voice>
        <type>quarter</type>
        <stem>none</stem>
        </note>
      <note default-x="259.10" default-y="0.00">
        <pitch>
          <step>F</step>
          <octave>4</octave>
          </pitch>
        <duration>1</duration>
        <voice>1</voice>
        <type>quarter</type>
        <stem>none</stem>
        </note>
      <note default-x="286.10" default-y="-5.00">
        <pitch>
          <step>E</step>
          <octave>4</octave>
          </pitch>
        <duration>1</duration>
        <voice>1</voice>
        <type>quarter</type>
        <stem>none</stem>
        </note>
      <note default-x="313.11" default-y="-10.00">
        <pitch>
          <step>D</step>
          <octave>4</octave>
          </pitch>
        <duration>1</duration>
        <voice>1</voice>
        <type>quarter</type>
        <stem>none</stem>
        </note>
      <note default-x="340.11" default-y="-15.00">
        <pitch>
          <step>C</step>
          <octave>4</octave>
          </pitch>
        <duration>1</duration>
        <voice>1</voice>
        <type>quarter</type>
        <stem>none</stem>
        </note>
      <note default-x="367.12" default-y="-20.00">
        <pitch>
          <step>B</step>
          <alter>-1</alter>
          <octave>3</octave>
          </pitch>
        <duration>1</duration>
        <voice>1</voice>
        <type>quarter</type>
        <stem>none</stem>
        <notations>
          <slur type="stop" number="1"/>
          </notations>
        </note>
      <note default-x="394.12" default-y="-15.00">
        <pitch>
          <step>C</step>
          <octave>4</octave>
          </pitch>
        <duration>1</duration>
        <voice>1</voice>
        <type>quarter</type>
        <stem>none</stem>
        <notations>
          <slur type="start" number="1"/>
          </notations>
        </note>
      <note default-x="421.13" default-y="-10.00">
        <pitch>
          <step>D</step>
          <octave>4</octave>
          </pitch>
        <duration>1</duration>
        <voice>1</voice>
        <type>quarter</type>
        <stem>none</stem>
        </note>
      <note default-x="448.14" default-y="-15.00">
        <pitch>
          <step>C</step>
          <octave>4</octave>
          </pitch>
        <duration>1</duration>
        <voice>1</voice>
        <type>quarter</type>
        <stem>none</stem>
        <notations>
          <slur type="stop" number="1"/>
          </notations>
        </note>
      <note default-x="475.14" default-y="-15.00">
        <pitch>
          <step>C</step>
          <octave>4</octave>
          </pitch>
        <duration>1</duration>
        <voice>1</voice>
        <type>quarter</type>
        <stem>none</stem>
        </note>
      <note default-x="502.15" default-y="-20.00">
        <pitch>
          <step>B</step>
          <alter>-1</alter>
          <octave>3</octave>
          </pitch>
        <duration>1</duration>
        <voice>1</voice>
        <type>quarter</type>
        <stem>none</stem>
        <notations>
          <slur type="start" number="1"/>
          </notations>
        <lyric number="1">
          <syllabic>end</syllabic>
          <text>ma</text>
          </lyric>
        </note>
      <note default-x="529.15" default-y="-30.00">
        <pitch>
          <step>G</step>
          <octave>3</octave>
          </pitch>
        <duration>1</duration>
        <voice>1</voice>
        <type>quarter</type>
        <stem>none</stem>
        </note>
      <note default-x="556.16" default-y="-25.00">
        <pitch>
          <step>A</step>
          <octave>3</octave>
          </pitch>
        <duration>1</duration>
        <voice>1</voice>
        <type>quarter</type>
        <stem>none</stem>
        <notations>
          <slur type="stop" number="1"/>
          <articulations>
            <breath-mark/>
            </articulations>
          </notations>
        </note>
      <note default-x="603.79" default-y="-15.00">
        <pitch>
          <step>C</step>
          <octave>4</octave>
          </pitch>
        <duration>1</duration>
        <voice>1</voice>
        <type>quarter</type>
        <stem>none</stem>
        <lyric number="1">
          <syllabic>begin</syllabic>
          <text>Re</text>
          </lyric>
        </note>
      <note default-x="642.91" default-y="-15.00">
        <pitch>
          <step>C</step>
          <octave>4</octave>
          </pitch>
        <duration>1</duration>
        <voice>1</voice>
        <type>quarter</type>
        <stem>none</stem>
        <lyric number="1">
          <syllabic>middle</syllabic>
          <text>demp</text>
          </lyric>
        </note>
      <note default-x="678.42" default-y="-35.00">
        <pitch>
          <step>F</step>
          <octave>3</octave>
          </pitch>
        <duration>1</duration>
        <voice>1</voice>
        <type>quarter</type>
        <stem>none</stem>
        <lyric number="1">
          <syllabic>middle</syllabic>
          <text>tor</text>
          </lyric>
        </note>
      <note default-x="705.42" default-y="-30.00">
        <pitch>
          <step>G</step>
          <octave>3</octave>
          </pitch>
        <duration>1</duration>
        <voice>1</voice>
        <type>quarter</type>
        <stem>none</stem>
        <notations>
          <slur type="start" number="1"/>
          </notations>
        </note>
      <note default-x="732.43" default-y="-25.00">
        <pitch>
          <step>A</step>
          <octave>3</octave>
          </pitch>
        <duration>1</duration>
        <voice>1</voice>
        <type>quarter</type>
        <stem>none</stem>
        </note>
      <note default-x="759.43" default-y="-30.00">
        <pitch>
          <step>G</step>
          <octave>3</octave>
          </pitch>
        <duration>1</duration>
        <voice>1</voice>
        <type>quarter</type>
        <stem>none</stem>
        </note>
      <note default-x="786.44" default-y="-25.00">
        <pitch>
          <step>A</step>
          <octave>3</octave>
          </pitch>
        <duration>1</duration>
        <voice>1</voice>
        <type>quarter</type>
        <stem>none</stem>
        <notations>
          <slur type="stop" number="1"/>
          <articulations>
            <breath-mark/>
            </articulations>
          </notations>
        <lyric number="1">
          <syllabic>end</syllabic>
          <text>is</text>
          </lyric>
        </note>
      <note default-x="830.45" default-y="-20.00">
        <pitch>
          <step>B</step>
          <alter>-1</alter>
          <octave>3</octave>
          </pitch>
        <duration>1</duration>
        <voice>1</voice>
        <type>quarter</type>
        <stem>none</stem>
        <notations>
          <slur type="start" number="1"/>
          </notations>
        <lyric number="1">
          <syllabic>begin</syllabic>
          <text>ma</text>
          </lyric>
        </note>
      <note default-x="857.63" default-y="-25.00">
        <pitch>
          <step>A</step>
          <octave>3</octave>
          </pitch>
        <duration>1</duration>
        <voice>1</voice>
        <type>quarter</type>
        <stem>none</stem>
        </note>
      <note default-x="884.64" default-y="-30.00">
        <pitch>
          <step>G</step>
          <octave>3</octave>
          </pitch>
        <duration>1</duration>
        <voice>1</voice>
        <type>quarter</type>
        <stem>none</stem>
        </note>
      <note default-x="911.65" default-y="-35.00">
        <pitch>
          <step>F</step>
          <octave>3</octave>
          </pitch>
        <duration>1</duration>
        <voice>1</voice>
        <type>quarter</type>
        <stem>none</stem>
        </note>
      <note default-x="938.65" default-y="-30.00">
        <pitch>
          <step>G</step>
          <octave>3</octave>
          </pitch>
        <duration>1</duration>
        <voice>1</voice>
        <type>quarter</type>
        <stem>none</stem>
        <notations>
          <slur type="stop" number="1"/>
          </notations>
        </note>
      <note default-x="965.66" default-y="-35.00">
        <pitch>
          <step>F</step>
          <octave>3</octave>
          </pitch>
        <duration>1</duration>
        <voice>1</voice>
        <type>quarter</type>
        <stem>none</stem>
        <notations>
          <articulations>
            <breath-mark/>
            </articulations>
          </notations>
        <lyric number="1">
          <syllabic>end</syllabic>
          <text>ter,</text>
          </lyric>
        </note>
      <note default-x="1021.60" default-y="-15.00">
        <pitch>
          <step>C</step>
          <octave>4</octave>
          </pitch>
        <duration>1</duration>
        <voice>1</voice>
        <type>quarter</type>
        <stem>none</stem>
        <lyric number="1">
          <syllabic>single</syllabic>
          <text>quae</text>
          </lyric>
        </note>
      <note default-x="1053.20" default-y="-5.00">
        <pitch>
          <step>E</step>
          <octave>4</octave>
          </pitch>
        <duration>1</duration>
        <voice>1</voice>
        <type>quarter</type>
        <stem>none</stem>
        <notations>
          <slur type="start" number="1"/>
          </notations>
        <lyric number="1">
          <syllabic>begin</syllabic>
          <text>per</text>
          </lyric>
        </note>
      <note default-x="1082.01" default-y="0.00">
        <pitch>
          <step>F</step>
          <octave>4</octave>
          </pitch>
        <duration>1</duration>
        <voice>1</voice>
        <type>quarter</type>
        <stem>none</stem>
        <notations>
          <slur type="stop" number="1"/>
          </notations>
        </note>
      </measure>
    <measure number="2" width="1110.61">
      <print new-system="yes">
        <system-layout>
          <system-margins>
            <left-margin>0.00</left-margin>
            <right-margin>0.00</right-margin>
            </system-margins>
          <system-distance>150.00</system-distance>
          </system-layout>
        </print>
      <note default-x="64.78" default-y="-10.00">
        <pitch>
          <step>D</step>
          <octave>4</octave>
          </pitch>
        <duration>1</duration>
        <voice>1</voice>
        <type>quarter</type>
        <stem>none</stem>
        <notations>
          <slur type="start" number="1"/>
          </notations>
        <lyric number="1">
          <syllabic>begin</syllabic>
          <text>vi</text>
          </lyric>
        </note>
      <note default-x="90.89" default-y="-15.00">
        <pitch>
          <step>C</step>
          <octave>4</octave>
          </pitch>
        <duration>1</duration>
        <voice>1</voice>
        <type>quarter</type>
        <stem>none</stem>
        <notations>
          <slur type="stop" number="1"/>
          </notations>
        <lyric number="1">
          <syllabic>end</syllabic>
          <text>a</text>
          </lyric>
        </note>
      <note default-x="117.01" default-y="-20.00">
        <pitch>
          <step>B</step>
          <alter>-1</alter>
          <octave>3</octave>
          </pitch>
        <duration>1</duration>
        <voice>1</voice>
        <type>quarter</type>
        <stem>none</stem>
        <notations>
          <articulations>
            <breath-mark/>
            </articulations>
          </notations>
        <lyric number="1">
          <syllabic>end</syllabic>
          <text>a</text>
          </lyric>
        </note>
      <note default-x="166.67" default-y="-15.00">
        <pitch>
          <step>C</step>
          <octave>4</octave>
          </pitch>
        <duration>1</duration>
        <voice>1</voice>
        <type>quarter</type>
        <stem>none</stem>
        <lyric number="1">
          <syllabic>begin</syllabic>
          <text>coe</text>
          </lyric>
        </note>
      <note default-x="192.79" default-y="-15.00">
        <pitch>
          <step>C</step>
          <octave>4</octave>
          </pitch>
        <duration>1</duration>
        <voice>1</voice>
        <type>quarter</type>
        <stem>none</stem>
        <notations>
          <articulations>
            <breath-mark/>
            </articulations>
          </notations>
        <lyric number="1">
          <syllabic>end</syllabic>
          <text>li</text>
          </lyric>
        </note>
      <note default-x="235.90" default-y="-35.00">
        <pitch>
          <step>F</step>
          <octave>3</octave>
          </pitch>
        <duration>1</duration>
        <voice>1</voice>
        <type>quarter</type>
        <stem>none</stem>
        <notations>
          <slur type="start" number="1"/>
          </notations>
        <lyric number="1">
          <syllabic>begin</syllabic>
          <text>Por</text>
          </lyric>
        </note>
      <note default-x="267.40" default-y="-30.00">
        <pitch>
          <step>G</step>
          <octave>3</octave>
          </pitch>
        <duration>1</duration>
        <voice>1</voice>
        <type>quarter</type>
        <stem>none</stem>
        </note>
      <note default-x="293.51" default-y="-25.00">
        <pitch>
          <step>A</step>
          <octave>3</octave>
          </pitch>
        <duration>1</duration>
        <voice>1</voice>
        <type>quarter</type>
        <stem>none</stem>
        </note>
      <note default-x="319.62" default-y="-20.00">
        <pitch>
          <step>B</step>
          <alter>-1</alter>
          <octave>3</octave>
          </pitch>
        <duration>1</duration>
        <voice>1</voice>
        <type>quarter</type>
        <stem>none</stem>
        </note>
      <note default-x="345.73" default-y="-25.00">
        <pitch>
          <step>A</step>
          <octave>3</octave>
          </pitch>
        <duration>1</duration>
        <voice>1</voice>
        <type>quarter</type>
        <stem>none</stem>
        </note>
      <note default-x="371.84" default-y="-30.00">
        <pitch>
          <step>G</step>
          <octave>3</octave>
          </pitch>
        <duration>1</duration>
        <voice>1</voice>
        <type>quarter</type>
        <stem>none</stem>
        <notations>
          <slur type="stop" number="1"/>
          </notations>
        </note>
      <note default-x="397.95" default-y="-25.00">
        <pitch>
          <step>A</step>
          <octave>3</octave>
          </pitch>
        <duration>1</duration>
        <voice>1</voice>
        <type>quarter</type>
        <stem>none</stem>
        <notations>
          <articulations>
            <breath-mark/>
            </articulations>
          </notations>
        <lyric number="1">
          <syllabic>end</syllabic>
          <text>ta</text>
          </lyric>
        </note>
      <note default-x="441.07" default-y="-15.00">
        <pitch>
          <step>C</step>
          <octave>4</octave>
          </pitch>
        <duration>1</duration>
        <voice>1</voice>
        <type>quarter</type>
        <stem>none</stem>
        <notations>
          <slur type="start" number="1"/>
          </notations>
        <lyric number="1">
          <syllabic>begin</syllabic>
          <text>ma</text>
          </lyric>
        </note>
      <note default-x="468.25" default-y="-10.00">
        <pitch>
          <step>D</step>
          <octave>4</octave>
          </pitch>
        <duration>1</duration>
        <voice>1</voice>
        <type>quarter</type>
        <stem>none</stem>
        </note>
      <note default-x="494.36" default-y="-15.00">
        <pitch>
          <step>C</step>
          <octave>4</octave>
          </pitch>
        <duration>1</duration>
        <voice>1</voice>
        <type>quarter</type>
        <stem>none</stem>
        </note>
      <note default-x="520.48" default-y="-35.00">
        <pitch>
          <step>F</step>
          <octave>3</octave>
          </pitch>
        <duration>1</duration>
        <voice>1</voice>
        <type>quarter</type>
        <stem>none</stem>
        </note>
      <note default-x="546.59" default-y="-30.00">
        <pitch>
          <step>G</step>
          <octave>3</octave>
          </pitch>
        <duration>1</duration>
        <voice>1</voice>
        <type>quarter</type>
        <stem>none</stem>
        </note>
      <note default-x="572.70" default-y="-25.00">
        <pitch>
          <step>A</step>
          <octave>3</octave>
          </pitch>
        <duration>1</duration>
        <voice>1</voice>
        <type>quarter</type>
        <stem>none</stem>
        <notations>
          <slur type="stop" number="1"/>
          </notations>
        </note>
      <note default-x="602.44" default-y="-20.00">
        <pitch>
          <step>B</step>
          <alter>-1</alter>
          <octave>3</octave>
          </pitch>
        <duration>1</duration>
        <voice>1</voice>
        <type>quarter</type>
        <stem>none</stem>
        <notations>
          <slur type="start" number="1"/>
          </notations>
        <lyric number="1">
          <syllabic>end</syllabic>
          <text>nens,</text>
          </lyric>
        </note>
      <note default-x="635.68" default-y="-25.00">
        <pitch>
          <step>A</step>
          <octave>3</octave>
          </pitch>
        <duration>1</duration>
        <voice>1</voice>
        <type>quarter</type>
        <stem>none</stem>
        </note>
      <note default-x="661.79" default-y="-30.00">
        <pitch>
          <step>G</step>
          <octave>3</octave>
          </pitch>
        <duration>1</duration>
        <voice>1</voice>
        <type>quarter</type>
        <stem>none</stem>
        <notations>
          <slur type="stop" number="1"/>
          </notations>
        </note>
      <note default-x="687.90" default-y="-25.00">
        <pitch>
          <step>A</step>
          <octave>3</octave>
          </pitch>
        <duration>1</duration>
        <voice>1</voice>
        <type>quarter</type>
        <stem>none</stem>
        <notations>
          <articulations>
            <breath-mark/>
            </articulations>
          </notations>
        </note>
      <note default-x="730.41" default-y="0.00">
        <pitch>
          <step>F</step>
          <octave>4</octave>
          </pitch>
        <duration>1</duration>
        <voice>1</voice>
        <type>quarter</type>
        <stem>none</stem>
        <notations>
          <articulations>
            <breath-mark/>
            </articulations>
          </notations>
        <lyric number="1">
          <syllabic>single</syllabic>
          <text>et</text>
          </lyric>
        </note>
      <note default-x="773.52" default-y="-5.00">
        <pitch>
          <step>E</step>
          <octave>4</octave>
          </pitch>
        <duration>1</duration>
        <voice>1</voice>
        <type>quarter</type>
        <stem>none</stem>
        <notations>
          <slur type="start" number="1"/>
          </notations>
        <lyric number="1">
          <syllabic>begin</syllabic>
          <text>stel</text>
          </lyric>
        </note>
      <note default-x="803.71" default-y="0.00">
        <pitch>
          <step>F</step>
          <octave>4</octave>
          </pitch>
        <duration>1</duration>
        <voice>1</voice>
        <type>quarter</type>
        <stem>none</stem>
        </note>
      <note default-x="829.82" default-y="-5.00">
        <pitch>
          <step>E</step>
          <octave>4</octave>
          </pitch>
        <duration>1</duration>
        <voice>1</voice>
        <type>quarter</type>
        <stem>none</stem>
        </note>
      <note default-x="855.93" default-y="-10.00">
        <pitch>
          <step>D</step>
          <octave>4</octave>
          </pitch>
        <duration>1</duration>
        <voice>1</voice>
        <type>quarter</type>
        <stem>none</stem>
        </note>
      <note default-x="882.05" default-y="-15.00">
        <pitch>
          <step>C</step>
          <octave>4</octave>
          </pitch>
        <duration>1</duration>
        <voice>1</voice>
        <type>quarter</type>
        <stem>none</stem>
        <notations>
          <slur type="stop" number="1"/>
          </notations>
        </note>
      <note default-x="908.16" default-y="-20.00">
        <pitch>
          <step>B</step>
          <alter>-1</alter>
          <octave>3</octave>
          </pitch>
        <duration>1</duration>
        <voice>1</voice>
        <type>quarter</type>
        <stem>none</stem>
        <notations>
          <articulations>
            <breath-mark/>
            </articulations>
          </notations>
        <lyric number="1">
          <syllabic>end</syllabic>
          <text>la</text>
          </lyric>
        </note>
      <note default-x="951.27" default-y="-15.00">
        <pitch>
          <step>C</step>
          <octave>4</octave>
          </pitch>
        <duration>1</duration>
        <voice>1</voice>
        <type>quarter</type>
        <stem>none</stem>
        <notations>
          <slur type="start" number="1"/>
          </notations>
        <lyric number="1">
          <syllabic>begin</syllabic>
          <text>ma</text>
          </lyric>
        </note>
      <note default-x="978.46" default-y="-10.00">
        <pitch>
          <step>D</step>
          <octave>4</octave>
          </pitch>
        <duration>1</duration>
        <voice>1</voice>
        <type>quarter</type>
        <stem>none</stem>
        </note>
      <note default-x="1004.57" default-y="-15.00">
        <pitch>
          <step>C</step>
          <octave>4</octave>
          </pitch>
        <duration>1</duration>
        <voice>1</voice>
        <type>quarter</type>
        <stem>none</stem>
        </note>
      <note default-x="1030.68" default-y="-20.00">
        <pitch>
          <step>B</step>
          <alter>-1</alter>
          <octave>3</octave>
          </pitch>
        <duration>1</duration>
        <voice>1</voice>
        <type>quarter</type>
        <stem>none</stem>
        </note>
      <note default-x="1056.79" default-y="-25.00">
        <pitch>
          <step>A</step>
          <octave>3</octave>
          </pitch>
        <duration>1</duration>
        <voice>1</voice>
        <type>quarter</type>
        <stem>none</stem>
        </note>
      <note default-x="1082.90" default-y="-30.00">
        <pitch>
          <step>G</step>
          <octave>3</octave>
          </pitch>
        <duration>1</duration>
        <voice>1</voice>
        <type>quarter</type>
        <stem>none</stem>
        <notations>
          <slur type="stop" number="1"/>
          </notations>
        </note>
      </measure>
    <measure number="3" width="1110.61">
      <print new-system="yes">
        <system-layout>
          <system-margins>
            <left-margin>0.00</left-margin>
            <right-margin>0.00</right-margin>
            </system-margins>
          <system-distance>150.00</system-distance>
          </system-layout>
        </print>
      <note default-x="68.45" default-y="-25.00">
        <pitch>
          <step>A</step>
          <octave>3</octave>
          </pitch>
        <duration>1</duration>
        <voice>1</voice>
        <type>quarter</type>
        <stem>none</stem>
        <notations>
          <articulations>
            <breath-mark/>
            </articulations>
          </notations>
        <lyric number="1">
          <syllabic>end</syllabic>
          <text>ris,</text>
          </lyric>
        </note>
      <note default-x="116.53" default-y="-35.00">
        <pitch>
          <step>F</step>
          <octave>3</octave>
          </pitch>
        <duration>1</duration>
        <voice>1</voice>
        <type>quarter</type>
        <stem>none</stem>
        <lyric number="1">
          <syllabic>begin</syllabic>
          <text>suc</text>
          </lyric>
        </note>
      <note default-x="141.90" default-y="-30.00">
        <pitch>
          <step>G</step>
          <octave>3</octave>
          </pitch>
        <duration>1</duration>
        <voice>1</voice>
        <type>quarter</type>
        <stem>none</stem>
        <notations>
          <slur type="start" number="1"/>
          </notations>
        <lyric number="1">
          <syllabic>middle</syllabic>
          <text>cur</text>
          </lyric>
        </note>
      <note default-x="170.47" default-y="-20.00">
        <pitch>
          <step>B</step>
          <alter>-1</alter>
          <octave>3</octave>
          </pitch>
        <duration>1</duration>
        <voice>1</voice>
        <type>quarter</type>
        <stem>none</stem>
        <notations>
          <slur type="stop" number="1"/>
          </notations>
        </note>
      <note default-x="195.84" default-y="-20.00">
        <pitch>
          <step>B</step>
          <alter>-1</alter>
          <octave>3</octave>
          </pitch>
        <duration>1</duration>
        <voice>1</voice>
        <type>quarter</type>
        <stem>none</stem>
        <notations>
          <articulations>
            <breath-mark/>
            </articulations>
          </notations>
        <lyric number="1">
          <syllabic>end</syllabic>
          <text>re</text>
          </lyric>
        </note>
      <note default-x="239.29" default-y="-20.00">
        <pitch>
          <step>B</step>
          <alter>-1</alter>
          <octave>3</octave>
          </pitch>
        <duration>1</duration>
        <voice>1</voice>
        <type>quarter</type>
        <stem>none</stem>
        <lyric number="1">
          <syllabic>begin</syllabic>
          <text>ca</text>
          </lyric>
        </note>
      <note default-x="264.66" default-y="-25.00">
        <pitch>
          <step>A</step>
          <octave>3</octave>
          </pitch>
        <duration>1</duration>
        <voice>1</voice>
        <type>quarter</type>
        <stem>none</stem>
        <notations>
          <slur type="start" number="1"/>
          </notations>
        <lyric number="1">
          <syllabic>middle</syllabic>
          <text>den</text>
          </lyric>
        </note>
      <note default-x="296.63" default-y="-20.00">
        <pitch>
          <step>B</step>
          <alter>-1</alter>
          <octave>3</octave>
          </pitch>
        <duration>1</duration>
        <voice>1</voice>
        <type>quarter</type>
        <stem>none</stem>
        </note>
      <note default-x="322.01" default-y="-25.00">
        <pitch>
          <step>A</step>
          <octave>3</octave>
          </pitch>
        <duration>1</duration>
        <voice>1</voice>
        <type>quarter</type>
        <stem>none</stem>
        </note>
      <note default-x="347.38" default-y="-30.00">
        <pitch>
          <step>G</step>
          <octave>3</octave>
          </pitch>
        <duration>1</duration>
        <voice>1</voice>
        <type>quarter</type>
        <stem>none</stem>
        <notations>
          <slur type="stop" number="1"/>
          </notations>
        </note>
      <note default-x="372.76" default-y="-35.00">
        <pitch>
          <step>F</step>
          <octave>3</octave>
          </pitch>
        <duration>1</duration>
        <voice>1</voice>
        <type>quarter</type>
        <stem>none</stem>
        <notations>
          <slur type="start" number="1"/>
          </notations>
        </note>
      <note default-x="398.13" default-y="-30.00">
        <pitch>
          <step>G</step>
          <octave>3</octave>
          </pitch>
        <duration>1</duration>
        <voice>1</voice>
        <type>quarter</type>
        <stem>none</stem>
        <notations>
          <slur type="stop" number="1"/>
          </notations>
        </note>
      <note default-x="423.51" default-y="-35.00">
        <pitch>
          <step>F</step>
          <octave>3</octave>
          </pitch>
        <duration>1</duration>
        <voice>1</voice>
        <type>quarter</type>
        <stem>none</stem>
        <notations>
          <articulations>
            <breath-mark/>
            </articulations>
          </notations>
        <lyric number="1">
          <syllabic>end</syllabic>
          <text>ti,</text>
          </lyric>
        </note>
      <note default-x="472.27" default-y="-15.00">
        <pitch>
          <step>C</step>
          <octave>4</octave>
          </pitch>
        <duration>1</duration>
        <voice>1</voice>
        <type>quarter</type>
        <stem>none</stem>
        <lyric number="1">
          <syllabic>begin</syllabic>
          <text>Sur</text>
          </lyric>
        </note>
      <note default-x="499.74" default-y="-15.00">
        <pitch>
          <step>C</step>
          <octave>4</octave>
          </pitch>
        <duration>1</duration>
        <voice>1</voice>
        <type>quarter</type>
        <stem>none</stem>
        <lyric number="1">
          <syllabic>middle</syllabic>
          <text>ge</text>
          </lyric>
        </note>
      <note default-x="525.11" default-y="-15.00">
        <pitch>
          <step>C</step>
          <octave>4</octave>
          </pitch>
        <duration>1</duration>
        <voice>1</voice>
        <type>quarter</type>
        <stem>none</stem>
        <notations>
          <articulations>
            <breath-mark/>
            </articulations>
          </notations>
        <lyric number="1">
          <syllabic>end</syllabic>
          <text>re</text>
          </lyric>
        </note>
      <note default-x="572.81" default-y="-20.00">
        <pitch>
          <step>B</step>
          <alter>-1</alter>
          <octave>3</octave>
          </pitch>
        <duration>1</duration>
        <voice>1</voice>
        <type>quarter</type>
        <stem>none</stem>
        <notations>
          <articulations>
            <breath-mark/>
            </articulations>
          </notations>
        <lyric number="1">
          <syllabic>single</syllabic>
          <text>qui</text>
          </lyric>
        </note>
      <note default-x="615.19" default-y="-15.00">
        <pitch>
          <step>C</step>
          <octave>4</octave>
          </pitch>
        <duration>1</duration>
        <voice>1</voice>
        <type>quarter</type>
        <stem>none</stem>
        <notations>
          <slur type="start" number="1"/>
          </notations>
        <lyric number="1">
          <syllabic>begin</syllabic>
          <text>cu</text>
          </lyric>
        </note>
      <note default-x="640.56" default-y="-10.00">
        <pitch>
          <step>D</step>
          <octave>4</octave>
          </pitch>
        <duration>1</duration>
        <voice>1</voice>
        <type>quarter</type>
        <stem>none</stem>
        </note>
      <note default-x="665.94" default-y="-15.00">
        <pitch>
          <step>C</step>
          <octave>4</octave>
          </pitch>
        <duration>1</duration>
        <voice>1</voice>
        <type>quarter</type>
        <stem>none</stem>
        <notations>
          <slur type="stop" number="1"/>
          </notations>
        </note>
      <note default-x="691.31" default-y="-20.00">
        <pitch>
          <step>B</step>
          <alter>-1</alter>
          <octave>3</octave>
          </pitch>
        <duration>1</duration>
        <voice>1</voice>
        <type>quarter</type>
        <stem>none</stem>
        <notations>
          <slur type="start" number="1"/>
          </notations>
        <lyric number="1">
          <syllabic>end</syllabic>
          <text>rat,</text>
          </lyric>
        </note>
      <note default-x="716.69" default-y="-25.00">
        <pitch>
          <step>A</step>
          <octave>3</octave>
          </pitch>
        <duration>1</duration>
        <voice>1</voice>
        <type>quarter</type>
        <stem>none</stem>
        <notations>
          <slur type="stop" number="1"/>
          <articulations>
            <breath-mark/>
            </articulations>
          </notations>
        </note>
      <note default-x="759.06" default-y="-30.00">
        <pitch>
          <step>G</step>
          <octave>3</octave>
          </pitch>
        <duration>1</duration>
        <voice>1</voice>
        <type>quarter</type>
        <stem>none</stem>
        <notations>
          <slur type="start" number="1"/>
          </notations>
        <lyric number="1">
          <syllabic>begin</syllabic>
          <text>Po</text>
          </lyric>
        </note>
      <note default-x="784.44" default-y="-25.00">
        <pitch>
          <step>A</step>
          <octave>3</octave>
          </pitch>
        <duration>1</duration>
        <voice>1</voice>
        <type>quarter</type>
        <stem>none</stem>
        <notations>
          <slur type="stop" number="1"/>
          </notations>
        </note>
      <note default-x="809.81" default-y="-20.00">
        <pitch>
          <step>B</step>
          <alter>-1</alter>
          <octave>3</octave>
          </pitch>
        <duration>1</duration>
        <voice>1</voice>
        <type>quarter</type>
        <stem>none</stem>
        <notations>
          <slur type="start" number="1"/>
          </notations>
        <lyric number="1">
          <syllabic>middle</syllabic>
          <text>pu</text>
          </lyric>
        </note>
      <note default-x="835.19" default-y="-25.00">
        <pitch>
          <step>A</step>
          <octave>3</octave>
          </pitch>
        <duration>1</duration>
        <voice>1</voice>
        <type>quarter</type>
        <stem>none</stem>
        </note>
      <note default-x="860.56" default-y="-30.00">
        <pitch>
          <step>G</step>
          <octave>3</octave>
          </pitch>
        <duration>1</duration>
        <voice>1</voice>
        <type>quarter</type>
        <stem>none</stem>
        <notations>
          <slur type="stop" number="1"/>
          </notations>
        </note>
      <note default-x="885.94" default-y="-25.00">
        <pitch>
          <step>A</step>
          <octave>3</octave>
          </pitch>
        <duration>1</duration>
        <voice>1</voice>
        <type>quarter</type>
        <stem>none</stem>
        <notations>
          <articulations>
            <breath-mark/>
            </articulations>
          </notations>
        <lyric number="1">
          <syllabic>end</syllabic>
          <text>lo,</text>
          </lyric>
        </note>
      <note default-x="931.76" default-y="0.00">
        <pitch>
          <step>F</step>
          <octave>4</octave>
          </pitch>
        <duration>1</duration>
        <voice>1</voice>
        <type>quarter</type>
        <stem>none</stem>
        <lyric number="1">
          <syllabic>single</syllabic>
          <text>Tu</text>
          </lyric>
        </note>
      <note default-x="957.14" default-y="0.00">
        <pitch>
          <step>F</step>
          <octave>4</octave>
          </pitch>
        <duration>1</duration>
        <voice>1</voice>
        <type>quarter</type>
        <stem>none</stem>
        <notations>
          <slur type="start" number="1"/>
          </notations>
        </note>
      <note default-x="982.51" default-y="-10.00">
        <pitch>
          <step>D</step>
          <octave>4</octave>
          </pitch>
        <duration>1</duration>
        <voice>1</voice>
        <type>quarter</type>
        <stem>none</stem>
        </note>
      <note default-x="1007.89" default-y="-15.00">
        <pitch>
          <step>C</step>
          <octave>4</octave>
          </pitch>
        <duration>1</duration>
        <voice>1</voice>
        <type>quarter</type>
        <stem>none</stem>
        </note>
      <note default-x="1033.26" default-y="-10.00">
        <pitch>
          <step>D</step>
          <octave>4</octave>
          </pitch>
        <duration>1</duration>
        <voice>1</voice>
        <type>quarter</type>
        <stem>none</stem>
        <notations>
          <slur type="stop" number="1"/>
          </notations>
        </note>
      <note default-x="1058.64" default-y="0.00">
        <pitch>
          <step>F</step>
          <octave>4</octave>
          </pitch>
        <duration>1</duration>
        <voice>1</voice>
        <type>quarter</type>
        <stem>none</stem>
        <notations>
          <articulations>
            <breath-mark/>
            </articulations>
          </notations>
        </note>
      </measure>
    <measure number="4" width="1110.61">
      <print new-system="yes">
        <system-layout>
          <system-margins>
            <left-margin>0.00</left-margin>
            <right-margin>0.00</right-margin>
            </system-margins>
          <system-distance>150.00</system-distance>
          </system-layout>
        </print>
      <note default-x="77.11" default-y="0.00">
        <pitch>
          <step>F</step>
          <octave>4</octave>
          </pitch>
        <duration>1</duration>
        <voice>1</voice>
        <type>quarter</type>
        <stem>none</stem>
        <notations>
          <articulations>
            <breath-mark/>
            </articulations>
          </notations>
        <lyric number="1">
          <syllabic>single</syllabic>
          <text>quae</text>
          </lyric>
        </note>
      <note default-x="122.63" default-y="-5.00">
        <pitch>
          <step>E</step>
          <octave>4</octave>
          </pitch>
        <duration>1</duration>
        <voice>1</voice>
        <type>quarter</type>
        <stem>none</stem>
        <lyric number="1">
          <syllabic>begin</syllabic>
          <text>ge</text>
          </lyric>
        </note>
      <note default-x="144.43" default-y="0.00">
        <pitch>
          <step>F</step>
          <octave>4</octave>
          </pitch>
        <duration>1</duration>
        <voice>1</voice>
        <type>quarter</type>
        <stem>none</stem>
        <notations>
          <slur type="start" number="1"/>
          </notations>
        <lyric number="1">
          <syllabic>middle</syllabic>
          <text>nu</text>
          </lyric>
        </note>
      <note default-x="166.43" default-y="5.00">
        <pitch>
          <step>G</step>
          <octave>4</octave>
          </pitch>
        <duration>1</duration>
        <voice>1</voice>
        <type>quarter</type>
        <stem>none</stem>
        <notations>
          <slur type="stop" number="1"/>
          </notations>
        </note>
      <note default-x="188.24" default-y="0.00">
        <pitch>
          <step>F</step>
          <octave>4</octave>
          </pitch>
        <duration>1</duration>
        <voice>1</voice>
        <type>quarter</type>
        <stem>none</stem>
        <notations>
          <slur type="start" number="1"/>
          </notations>
        <lyric number="1">
          <syllabic>middle</syllabic>
          <text>is</text>
          </lyric>
        </note>
      <note default-x="210.05" default-y="-5.00">
        <pitch>
          <step>E</step>
          <octave>4</octave>
          </pitch>
        <duration>1</duration>
        <voice>1</voice>
        <type>quarter</type>
        <stem>none</stem>
        <notations>
          <slur type="stop" number="1"/>
          </notations>
        </note>
      <note default-x="231.86" default-y="-10.00">
        <pitch>
          <step>D</step>
          <octave>4</octave>
          </pitch>
        <duration>1</duration>
        <voice>1</voice>
        <type>quarter</type>
        <stem>none</stem>
        <notations>
          <slur type="start" number="1"/>
          </notations>
        <lyric number="1">
          <syllabic>end</syllabic>
          <text>ti</text>
          </lyric>
        </note>
      <note default-x="253.67" default-y="-15.00">
        <pitch>
          <step>C</step>
          <octave>4</octave>
          </pitch>
        <duration>1</duration>
        <voice>1</voice>
        <type>quarter</type>
        <stem>none</stem>
        <notations>
          <slur type="stop" number="1"/>
          <articulations>
            <breath-mark/>
            </articulations>
          </notations>
        </note>
      <note default-x="292.48" default-y="-20.00">
        <pitch>
          <step>B</step>
          <alter>-1</alter>
          <octave>3</octave>
          </pitch>
        <duration>1</duration>
        <voice>1</voice>
        <type>quarter</type>
        <stem>none</stem>
        <notations>
          <slur type="start" number="1"/>
          </notations>
        <lyric number="1">
          <syllabic>begin</syllabic>
          <text>Na</text>
          </lyric>
        </note>
      <note default-x="318.48" default-y="-15.00">
        <pitch>
          <step>C</step>
          <octave>4</octave>
          </pitch>
        <duration>1</duration>
        <voice>1</voice>
        <type>quarter</type>
        <stem>none</stem>
        <notations>
          <slur type="stop" number="1"/>
          </notations>
        </note>
      <note default-x="340.28" default-y="-10.00">
        <pitch>
          <step>D</step>
          <octave>4</octave>
          </pitch>
        <duration>1</duration>
        <voice>1</voice>
        <type>quarter</type>
        <stem>none</stem>
        <notations>
          <slur type="start" number="1"/>
          </notations>
        <lyric number="1">
          <syllabic>middle</syllabic>
          <text>tu</text>
          </lyric>
        </note>
      <note default-x="362.09" default-y="-15.00">
        <pitch>
          <step>C</step>
          <octave>4</octave>
          </pitch>
        <duration>1</duration>
        <voice>1</voice>
        <type>quarter</type>
        <stem>none</stem>
        </note>
      <note default-x="383.90" default-y="-20.00">
        <pitch>
          <step>B</step>
          <alter>-1</alter>
          <octave>3</octave>
          </pitch>
        <duration>1</duration>
        <voice>1</voice>
        <type>quarter</type>
        <stem>none</stem>
        </note>
      <note default-x="405.71" default-y="-25.00">
        <pitch>
          <step>A</step>
          <octave>3</octave>
          </pitch>
        <duration>1</duration>
        <voice>1</voice>
        <type>quarter</type>
        <stem>none</stem>
        </note>
      <note default-x="427.52" default-y="-30.00">
        <pitch>
          <step>G</step>
          <octave>3</octave>
          </pitch>
        <duration>1</duration>
        <voice>1</voice>
        <type>quarter</type>
        <stem>none</stem>
        <notations>
          <slur type="stop" number="1"/>
          </notations>
        </note>
      <note default-x="449.32" default-y="-25.00">
        <pitch>
          <step>A</step>
          <octave>3</octave>
          </pitch>
        <duration>1</duration>
        <voice>1</voice>
        <type>quarter</type>
        <stem>none</stem>
        <notations>
          <articulations>
            <breath-mark/>
            </articulations>
          </notations>
        <lyric number="1">
          <syllabic>end</syllabic>
          <text>ra</text>
          </lyric>
        </note>
      <note default-x="491.16" default-y="-20.00">
        <pitch>
          <step>B</step>
          <alter>-1</alter>
          <octave>3</octave>
          </pitch>
        <duration>1</duration>
        <voice>1</voice>
        <type>quarter</type>
        <stem>none</stem>
        <lyric number="1">
          <syllabic>begin</syllabic>
          <text>mi</text>
          </lyric>
        </note>
      <note default-x="513.85" default-y="-25.00">
        <pitch>
          <step>A</step>
          <octave>3</octave>
          </pitch>
        <duration>1</duration>
        <voice>1</voice>
        <type>quarter</type>
        <stem>none</stem>
        <notations>
          <slur type="start" number="1"/>
          </notations>
        <lyric number="1">
          <syllabic>middle</syllabic>
          <text>ran</text>
          </lyric>
        </note>
      <note default-x="542.23" default-y="-30.00">
        <pitch>
          <step>G</step>
          <octave>3</octave>
          </pitch>
        <duration>1</duration>
        <voice>1</voice>
        <type>quarter</type>
        <stem>none</stem>
        </note>
      <note default-x="564.03" default-y="-35.00">
        <pitch>
          <step>F</step>
          <octave>3</octave>
          </pitch>
        <duration>1</duration>
        <voice>1</voice>
        <type>quarter</type>
        <stem>none</stem>
        </note>
      <note default-x="585.84" default-y="-30.00">
        <pitch>
          <step>G</step>
          <octave>3</octave>
          </pitch>
        <duration>1</duration>
        <voice>1</voice>
        <type>quarter</type>
        <stem>none</stem>
        <notations>
          <slur type="stop" number="1"/>
          </notations>
        </note>
      <note default-x="607.65" default-y="-35.00">
        <pitch>
          <step>F</step>
          <octave>3</octave>
          </pitch>
        <duration>1</duration>
        <voice>1</voice>
        <type>quarter</type>
        <stem>none</stem>
        <notations>
          <articulations>
            <breath-mark/>
            </articulations>
          </notations>
        <lyric number="1">
          <syllabic>end</syllabic>
          <text>te</text>
          </lyric>
        </note>
      <note default-x="646.36" default-y="-35.00">
        <pitch>
          <step>F</step>
          <octave>3</octave>
          </pitch>
        <duration>1</duration>
        <voice>1</voice>
        <type>quarter</type>
        <stem>none</stem>
        <lyric number="1">
          <syllabic>begin</syllabic>
          <text>tu</text>
          </lyric>
        </note>
      <note default-x="671.28" default-y="-30.00">
        <pitch>
          <step>G</step>
          <octave>3</octave>
          </pitch>
        <duration>1</duration>
        <voice>1</voice>
        <type>quarter</type>
        <stem>none</stem>
        <notations>
          <slur type="start" number="1"/>
          </notations>
        <lyric number="1">
          <syllabic>end</syllabic>
          <text>um</text>
          </lyric>
        </note>
      <note default-x="694.30" default-y="-25.00">
        <pitch>
          <step>A</step>
          <octave>3</octave>
          </pitch>
        <duration>1</duration>
        <voice>1</voice>
        <type>quarter</type>
        <stem>none</stem>
        </note>
      <note default-x="716.11" default-y="-30.00">
        <pitch>
          <step>G</step>
          <octave>3</octave>
          </pitch>
        <duration>1</duration>
        <voice>1</voice>
        <type>quarter</type>
        <stem>none</stem>
        </note>
      <note default-x="737.92" default-y="-25.00">
        <pitch>
          <step>A</step>
          <octave>3</octave>
          </pitch>
        <duration>1</duration>
        <voice>1</voice>
        <type>quarter</type>
        <stem>none</stem>
        <notations>
          <slur type="stop" number="1"/>
          <articulations>
            <breath-mark/>
            </articulations>
          </notations>
        </note>
      <note default-x="787.21" default-y="-20.00">
        <pitch>
          <step>B</step>
          <alter>-1</alter>
          <octave>3</octave>
          </pitch>
        <duration>1</duration>
        <voice>1</voice>
        <type>quarter</type>
        <stem>none</stem>
        <lyric number="1">
          <syllabic>begin</syllabic>
          <text>sanc</text>
          </lyric>
        </note>
      <note default-x="825.82" default-y="-25.00">
        <pitch>
          <step>A</step>
          <octave>3</octave>
          </pitch>
        <duration>1</duration>
        <voice>1</voice>
        <type>quarter</type>
        <stem>none</stem>
        <notations>
          <slur type="start" number="1"/>
          </notations>
        <lyric number="1">
          <syllabic>end</syllabic>
          <text>tum</text>
          </lyric>
        </note>
      <note default-x="851.95" default-y="-30.00">
        <pitch>
          <step>G</step>
          <octave>3</octave>
          </pitch>
        <duration>1</duration>
        <voice>1</voice>
        <type>quarter</type>
        <stem>none</stem>
        </note>
      <note default-x="873.75" default-y="-25.00">
        <pitch>
          <step>A</step>
          <octave>3</octave>
          </pitch>
        <duration>1</duration>
        <voice>1</voice>
        <type>quarter</type>
        <stem>none</stem>
        <notations>
          <slur type="stop" number="1"/>
          <articulations>
            <breath-mark/>
            </articulations>
          </notations>
        </note>
      <note default-x="912.56" default-y="-20.00">
        <pitch>
          <step>B</step>
          <alter>-1</alter>
          <octave>3</octave>
          </pitch>
        <duration>1</duration>
        <voice>1</voice>
        <type>quarter</type>
        <stem>none</stem>
        <notations>
          <slur type="start" number="1"/>
          </notations>
        <lyric number="1">
          <syllabic>begin</syllabic>
          <text>ge</text>
          </lyric>
        </note>
      <note default-x="934.37" default-y="-25.00">
        <pitch>
          <step>A</step>
          <octave>3</octave>
          </pitch>
        <duration>1</duration>
        <voice>1</voice>
        <type>quarter</type>
        <stem>none</stem>
        <notations>
          <slur type="stop" number="1"/>
          </notations>
        </note>
      <note default-x="956.18" default-y="-30.00">
        <pitch>
          <step>G</step>
          <octave>3</octave>
          </pitch>
        <duration>1</duration>
        <voice>1</voice>
        <type>quarter</type>
        <stem>none</stem>
        <notations>
          <slur type="start" number="1"/>
          </notations>
        <lyric number="1">
          <syllabic>middle</syllabic>
          <text>ni</text>
          </lyric>
        </note>
      <note default-x="977.99" default-y="-35.00">
        <pitch>
          <step>F</step>
          <octave>3</octave>
          </pitch>
        <duration>1</duration>
        <voice>1</voice>
        <type>quarter</type>
        <stem>none</stem>
        <notations>
          <slur type="stop" number="1"/>
          </notations>
        </note>
      <note default-x="999.79" default-y="-45.00">
        <pitch>
          <step>D</step>
          <octave>3</octave>
          </pitch>
        <duration>1</duration>
        <voice>1</voice>
        <type>quarter</type>
        <stem>none</stem>
        <notations>
          <slur type="start" number="1"/>
          </notations>
        <lyric number="1">
          <syllabic>middle</syllabic>
          <text>to</text>
          </lyric>
        </note>
      <note default-x="1021.60" default-y="-35.00">
        <pitch>
          <step>F</step>
          <octave>3</octave>
          </pitch>
        <duration>1</duration>
        <voice>1</voice>
        <type>quarter</type>
        <stem>none</stem>
        </note>
      <note default-x="1043.41" default-y="-30.00">
        <pitch>
          <step>G</step>
          <octave>3</octave>
          </pitch>
        <duration>1</duration>
        <voice>1</voice>
        <type>quarter</type>
        <stem>none</stem>
        <notations>
          <slur type="stop" number="1"/>
          </notations>
        </note>
      <note default-x="1070.71" default-y="-35.00">
        <pitch>
          <step>F</step>
          <octave>3</octave>
          </pitch>
        <duration>1</duration>
        <voice>1</voice>
        <type>quarter</type>
        <stem>none</stem>
        <lyric number="1">
          <syllabic>end</syllabic>
          <text>rem.</text>
          </lyric>
        </note>
      </measure>
    <measure number="5" width="1110.61">
      <print new-system="yes">
        <system-layout>
          <system-margins>
            <left-margin>0.00</left-margin>
            <right-margin>0.00</right-margin>
            </system-margins>
          <system-distance>150.00</system-distance>
          </system-layout>
        </print>
      <note default-x="65.18" default-y="0.00">
        <pitch>
          <step>F</step>
          <octave>4</octave>
          </pitch>
        <duration>1</duration>
        <voice>1</voice>
        <type>quarter</type>
        <stem>none</stem>
        <notations>
          <slur type="start" number="1"/>
          </notations>
        <lyric number="1">
          <syllabic>begin</syllabic>
          <text>Vir</text>
          </lyric>
        </note>
      <note default-x="94.74" default-y="-5.00">
        <pitch>
          <step>E</step>
          <octave>4</octave>
          </pitch>
        <duration>1</duration>
        <voice>1</voice>
        <type>quarter</type>
        <stem>none</stem>
        </note>
      <note default-x="117.29" default-y="-10.00">
        <pitch>
          <step>D</step>
          <octave>4</octave>
          </pitch>
        <duration>1</duration>
        <voice>1</voice>
        <type>quarter</type>
        <stem>none</stem>
        <notations>
          <slur type="stop" number="1"/>
          </notations>
        </note>
      <note default-x="139.83" default-y="-15.00">
        <pitch>
          <step>C</step>
          <octave>4</octave>
          </pitch>
        <duration>1</duration>
        <voice>1</voice>
        <type>quarter</type>
        <stem>none</stem>
        <notations>
          <slur type="start" number="1"/>
          </notations>
        </note>
      <note default-x="162.38" default-y="-25.00">
        <pitch>
          <step>A</step>
          <octave>3</octave>
          </pitch>
        <duration>1</duration>
        <voice>1</voice>
        <type>quarter</type>
        <stem>none</stem>
        </note>
      <note default-x="184.92" default-y="-20.00">
        <pitch>
          <step>B</step>
          <alter>-1</alter>
          <octave>3</octave>
          </pitch>
        <duration>1</duration>
        <voice>1</voice>
        <type>quarter</type>
        <stem>none</stem>
        <notations>
          <slur type="stop" number="1"/>
          </notations>
        </note>
      <note default-x="207.47" default-y="-15.00">
        <pitch>
          <step>C</step>
          <octave>4</octave>
          </pitch>
        <duration>1</duration>
        <voice>1</voice>
        <type>quarter</type>
        <stem>none</stem>
        <notations>
          <articulations>
            <breath-mark/>
            </articulations>
          </notations>
        <lyric number="1">
          <syllabic>end</syllabic>
          <text>go</text>
          </lyric>
        </note>
      <note default-x="247.02" default-y="-15.00">
        <pitch>
          <step>C</step>
          <octave>4</octave>
          </pitch>
        <duration>1</duration>
        <voice>1</voice>
        <type>quarter</type>
        <stem>none</stem>
        <notations>
          <slur type="start" number="1"/>
          </notations>
        <lyric number="1">
          <syllabic>begin</syllabic>
          <text>pri</text>
          </lyric>
        </note>
      <note default-x="272.17" default-y="-20.00">
        <pitch>
          <step>B</step>
          <alter>-1</alter>
          <octave>3</octave>
          </pitch>
        <duration>1</duration>
        <voice>1</voice>
        <type>quarter</type>
        <stem>none</stem>
        </note>
      <note default-x="294.72" default-y="-25.00">
        <pitch>
          <step>A</step>
          <octave>3</octave>
          </pitch>
        <duration>1</duration>
        <voice>1</voice>
        <type>quarter</type>
        <stem>none</stem>
        </note>
      <note default-x="317.26" default-y="-30.00">
        <pitch>
          <step>G</step>
          <octave>3</octave>
          </pitch>
        <duration>1</duration>
        <voice>1</voice>
        <type>quarter</type>
        <stem>none</stem>
        </note>
      <note default-x="339.81" default-y="-25.00">
        <pitch>
          <step>A</step>
          <octave>3</octave>
          </pitch>
        <duration>1</duration>
        <voice>1</voice>
        <type>quarter</type>
        <stem>none</stem>
        </note>
      <note default-x="362.36" default-y="-20.00">
        <pitch>
          <step>B</step>
          <alter>-1</alter>
          <octave>3</octave>
          </pitch>
        <duration>1</duration>
        <voice>1</voice>
        <type>quarter</type>
        <stem>none</stem>
        </note>
      <note default-x="384.90" default-y="-25.00">
        <pitch>
          <step>A</step>
          <octave>3</octave>
          </pitch>
        <duration>1</duration>
        <voice>1</voice>
        <type>quarter</type>
        <stem>none</stem>
        <notations>
          <slur type="stop" number="1"/>
          </notations>
        </note>
      <note default-x="407.45" default-y="-30.00">
        <pitch>
          <step>G</step>
          <octave>3</octave>
          </pitch>
        <duration>1</duration>
        <voice>1</voice>
        <type>quarter</type>
        <stem>none</stem>
        <notations>
          <slur type="start" number="1"/>
          </notations>
        <lyric number="1">
          <syllabic>end</syllabic>
          <text>us</text>
          </lyric>
        </note>
      <note default-x="429.99" default-y="-35.00">
        <pitch>
          <step>F</step>
          <octave>3</octave>
          </pitch>
        <duration>1</duration>
        <voice>1</voice>
        <type>quarter</type>
        <stem>none</stem>
        <notations>
          <slur type="stop" number="1"/>
          <articulations>
            <breath-mark/>
            </articulations>
          </notations>
        </note>
      <note default-x="470.61" default-y="-15.00">
        <pitch>
          <step>C</step>
          <octave>4</octave>
          </pitch>
        <duration>1</duration>
        <voice>1</voice>
        <type>quarter</type>
        <stem>none</stem>
        <notations>
          <articulations>
            <breath-mark/>
            </articulations>
          </notations>
        <lyric number="1">
          <syllabic>single</syllabic>
          <text>ac</text>
          </lyric>
        </note>
      <note default-x="510.16" default-y="-5.00">
        <pitch>
          <step>E</step>
          <octave>4</octave>
          </pitch>
        <duration>1</duration>
        <voice>1</voice>
        <type>quarter</type>
        <stem>none</stem>
        <notations>
          <slur type="start" number="1"/>
          </notations>
        <lyric number="1">
          <syllabic>begin</syllabic>
          <text>pos</text>
          </lyric>
        </note>
      <note default-x="540.50" default-y="0.00">
        <pitch>
          <step>F</step>
          <octave>4</octave>
          </pitch>
        <duration>1</duration>
        <voice>1</voice>
        <type>quarter</type>
        <stem>none</stem>
        <notations>
          <slur type="stop" number="1"/>
          </notations>
        </note>
      <note default-x="563.05" default-y="-10.00">
        <pitch>
          <step>D</step>
          <octave>4</octave>
          </pitch>
        <duration>1</duration>
        <voice>1</voice>
        <type>quarter</type>
        <stem>none</stem>
        <notations>
          <slur type="start" number="1"/>
          </notations>
        <lyric number="1">
          <syllabic>middle</syllabic>
          <text>te</text>
          </lyric>
        </note>
      <note default-x="585.59" default-y="-15.00">
        <pitch>
          <step>C</step>
          <octave>4</octave>
          </pitch>
        <duration>1</duration>
        <voice>1</voice>
        <type>quarter</type>
        <stem>none</stem>
        <notations>
          <slur type="stop" number="1"/>
          </notations>
        </note>
      <note default-x="608.14" default-y="-20.00">
        <pitch>
          <step>B</step>
          <alter>-1</alter>
          <octave>3</octave>
          </pitch>
        <duration>1</duration>
        <voice>1</voice>
        <type>quarter</type>
        <stem>none</stem>
        <notations>
          <slur type="start" number="1"/>
          </notations>
        <lyric number="1">
          <syllabic>middle</syllabic>
          <text>ri</text>
          </lyric>
        </note>
      <note default-x="630.69" default-y="-15.00">
        <pitch>
          <step>C</step>
          <octave>4</octave>
          </pitch>
        <duration>1</duration>
        <voice>1</voice>
        <type>quarter</type>
        <stem>none</stem>
        <notations>
          <slur type="stop" number="1"/>
          </notations>
        </note>
      <note default-x="653.23" default-y="-15.00">
        <pitch>
          <step>C</step>
          <octave>4</octave>
          </pitch>
        <duration>1</duration>
        <voice>1</voice>
        <type>quarter</type>
        <stem>none</stem>
        <notations>
          <articulations>
            <breath-mark/>
            </articulations>
          </notations>
        <lyric number="1">
          <syllabic>end</syllabic>
          <text>us</text>
          </lyric>
        </note>
      <note default-x="696.91" default-y="-15.00">
        <pitch>
          <step>C</step>
          <octave>4</octave>
          </pitch>
        <duration>1</duration>
        <voice>1</voice>
        <type>quarter</type>
        <stem>none</stem>
        <lyric number="1">
          <syllabic>begin</syllabic>
          <text>Ga</text>
          </lyric>
        </note>
      <note default-x="724.46" default-y="-15.00">
        <pitch>
          <step>C</step>
          <octave>4</octave>
          </pitch>
        <duration>1</duration>
        <voice>1</voice>
        <type>quarter</type>
        <stem>none</stem>
        <lyric number="1">
          <syllabic>middle</syllabic>
          <text>bri</text>
          </lyric>
        </note>
      <note default-x="754.07" default-y="-15.00">
        <pitch>
          <step>C</step>
          <octave>4</octave>
          </pitch>
        <duration>1</duration>
        <voice>1</voice>
        <type>quarter</type>
        <stem>none</stem>
        <notations>
          <slur type="start" number="1"/>
          </notations>
        <lyric number="1">
          <syllabic>end</syllabic>
          <text>elis</text>
          </lyric>
        </note>
      <note default-x="777.93" default-y="-20.00">
        <pitch>
          <step>B</step>
          <alter>-1</alter>
          <octave>3</octave>
          </pitch>
        <duration>1</duration>
        <voice>1</voice>
        <type>quarter</type>
        <stem>none</stem>
        <notations>
          <slur type="stop" number="1"/>
          </notations>
        </note>
      <note default-x="800.48" default-y="-25.00">
        <pitch>
          <step>A</step>
          <octave>3</octave>
          </pitch>
        <duration>1</duration>
        <voice>1</voice>
        <type>quarter</type>
        <stem>none</stem>
        <notations>
          <articulations>
            <breath-mark/>
            </articulations>
          </notations>
        </note>
      <note default-x="841.73" default-y="-25.00">
        <pitch>
          <step>A</step>
          <octave>3</octave>
          </pitch>
        <duration>1</duration>
        <voice>1</voice>
        <type>quarter</type>
        <stem>none</stem>
        <notations>
          <slur type="start" number="1"/>
          </notations>
        <lyric number="1">
          <syllabic>single</syllabic>
          <text>ab</text>
          </lyric>
        </note>
      <note default-x="864.27" default-y="-20.00">
        <pitch>
          <step>B</step>
          <alter>-1</alter>
          <octave>3</octave>
          </pitch>
        <duration>1</duration>
        <voice>1</voice>
        <type>quarter</type>
        <stem>none</stem>
        </note>
      <note default-x="886.82" default-y="-15.00">
        <pitch>
          <step>C</step>
          <octave>4</octave>
          </pitch>
        <duration>1</duration>
        <voice>1</voice>
        <type>quarter</type>
        <stem>none</stem>
        <notations>
          <slur type="stop" number="1"/>
          <articulations>
            <breath-mark/>
            </articulations>
          </notations>
        </note>
      <note default-x="926.36" default-y="-15.00">
        <pitch>
          <step>C</step>
          <octave>4</octave>
          </pitch>
        <duration>1</duration>
        <voice>1</voice>
        <type>quarter</type>
        <stem>none</stem>
        <notations>
          <slur type="start" number="1"/>
          </notations>
        <lyric number="1">
          <syllabic>begin</syllabic>
          <text>o</text>
          </lyric>
        </note>
      <note default-x="948.91" default-y="-20.00">
        <pitch>
          <step>B</step>
          <alter>-1</alter>
          <octave>3</octave>
          </pitch>
        <duration>1</duration>
        <voice>1</voice>
        <type>quarter</type>
        <stem>none</stem>
        </note>
      <note default-x="971.45" default-y="-25.00">
        <pitch>
          <step>A</step>
          <octave>3</octave>
          </pitch>
        <duration>1</duration>
        <voice>1</voice>
        <type>quarter</type>
        <stem>none</stem>
        </note>
      <note default-x="994.00" default-y="-20.00">
        <pitch>
          <step>B</step>
          <alter>-1</alter>
          <octave>3</octave>
          </pitch>
        <duration>1</duration>
        <voice>1</voice>
        <type>quarter</type>
        <stem>none</stem>
        <notations>
          <slur type="stop" number="1"/>
          </notations>
        </note>
      <note default-x="1016.55" default-y="-30.00">
        <pitch>
          <step>G</step>
          <octave>3</octave>
          </pitch>
        <duration>1</duration>
        <voice>1</voice>
        <type>quarter</type>
        <stem>none</stem>
        <notations>
          <slur type="start" number="1"/>
          </notations>
        <lyric number="1">
          <syllabic>end</syllabic>
          <text>re</text>
          </lyric>
        </note>
      <note default-x="1039.09" default-y="-35.00">
        <pitch>
          <step>F</step>
          <octave>3</octave>
          </pitch>
        <duration>1</duration>
        <voice>1</voice>
        <type>quarter</type>
        <stem>none</stem>
        <notations>
          <slur type="stop" number="1"/>
          <articulations>
            <breath-mark/>
            </articulations>
          </notations>
        </note>
      <note default-x="1081.24" default-y="-35.00">
        <pitch>
          <step>F</step>
          <octave>3</octave>
          </pitch>
        <duration>1</duration>
        <voice>1</voice>
        <type>quarter</type>
        <stem>none</stem>
        <lyric number="1">
          <syllabic>begin</syllabic>
          <text>Su</text>
          </lyric>
        </note>
      </measure>
    <measure number="6" width="1110.61">
      <print new-system="yes">
        <system-layout>
          <system-margins>
            <left-margin>0.00</left-margin>
            <right-margin>0.00</right-margin>
            </system-margins>
          <system-distance>150.00</system-distance>
          </system-layout>
        </print>
      <note default-x="79.44" default-y="-30.00">
        <pitch>
          <step>G</step>
          <octave>3</octave>
          </pitch>
        <duration>1</duration>
        <voice>1</voice>
        <type>quarter</type>
        <stem>none</stem>
        <notations>
          <slur type="start" number="1"/>
          </notations>
        <lyric number="1">
          <syllabic>end</syllabic>
          <text>mens</text>
          </lyric>
        </note>
      <note default-x="111.37" default-y="-25.00">
        <pitch>
          <step>A</step>
          <octave>3</octave>
          </pitch>
        <duration>1</duration>
        <voice>1</voice>
        <type>quarter</type>
        <stem>none</stem>
        </note>
      <note default-x="134.70" default-y="-30.00">
        <pitch>
          <step>G</step>
          <octave>3</octave>
          </pitch>
        <duration>1</duration>
        <voice>1</voice>
        <type>quarter</type>
        <stem>none</stem>
        </note>
      <note default-x="158.04" default-y="-25.00">
        <pitch>
          <step>A</step>
          <octave>3</octave>
          </pitch>
        <duration>1</duration>
        <voice>1</voice>
        <type>quarter</type>
        <stem>none</stem>
        <notations>
          <slur type="stop" number="1"/>
          <articulations>
            <breath-mark/>
            </articulations>
          </notations>
        </note>
      <note default-x="196.38" default-y="-20.00">
        <pitch>
          <step>B</step>
          <alter>-1</alter>
          <octave>3</octave>
          </pitch>
        <duration>1</duration>
        <voice>1</voice>
        <type>quarter</type>
        <stem>none</stem>
        <lyric number="1">
          <syllabic>begin</syllabic>
          <text>il</text>
          </lyric>
        </note>
      <note default-x="219.72" default-y="-25.00">
        <pitch>
          <step>A</step>
          <octave>3</octave>
          </pitch>
        <duration>1</duration>
        <voice>1</voice>
        <type>quarter</type>
        <stem>none</stem>
        <notations>
          <slur type="start" number="1"/>
          </notations>
        <lyric number="1">
          <syllabic>end</syllabic>
          <text>lud</text>
          </lyric>
        </note>
      <note default-x="243.06" default-y="-30.00">
        <pitch>
          <step>G</step>
          <octave>3</octave>
          </pitch>
        <duration>1</duration>
        <voice>1</voice>
        <type>quarter</type>
        <stem>none</stem>
        <notations>
          <slur type="stop" number="1"/>
          <articulations>
            <breath-mark/>
            </articulations>
          </notations>
        </note>
      <note default-x="283.40" default-y="-35.00">
        <pitch>
          <step>F</step>
          <octave>3</octave>
          </pitch>
        <duration>1</duration>
        <voice>1</voice>
        <type>quarter</type>
        <stem>none</stem>
        <notations>
          <slur type="start" number="1"/>
          </notations>
        <lyric number="1">
          <syllabic>begin</syllabic>
          <text>A</text>
          </lyric>
        </note>
      <note default-x="306.74" default-y="-30.00">
        <pitch>
          <step>G</step>
          <octave>3</octave>
          </pitch>
        <duration>1</duration>
        <voice>1</voice>
        <type>quarter</type>
        <stem>none</stem>
        </note>
      <note default-x="330.07" default-y="-25.00">
        <pitch>
          <step>A</step>
          <octave>3</octave>
          </pitch>
        <duration>1</duration>
        <voice>1</voice>
        <type>quarter</type>
        <stem>none</stem>
        </note>
      <note default-x="353.41" default-y="-20.00">
        <pitch>
          <step>B</step>
          <alter>-1</alter>
          <octave>3</octave>
          </pitch>
        <duration>1</duration>
        <voice>1</voice>
        <type>quarter</type>
        <stem>none</stem>
        </note>
      <note default-x="376.75" default-y="-25.00">
        <pitch>
          <step>A</step>
          <octave>3</octave>
          </pitch>
        <duration>1</duration>
        <voice>1</voice>
        <type>quarter</type>
        <stem>none</stem>
        </note>
      <note default-x="400.09" default-y="-30.00">
        <pitch>
          <step>G</step>
          <octave>3</octave>
          </pitch>
        <duration>1</duration>
        <voice>1</voice>
        <type>quarter</type>
        <stem>none</stem>
        <notations>
          <slur type="stop" number="1"/>
          </notations>
        </note>
      <note default-x="423.43" default-y="-25.00">
        <pitch>
          <step>A</step>
          <octave>3</octave>
          </pitch>
        <duration>1</duration>
        <voice>1</voice>
        <type>quarter</type>
        <stem>none</stem>
        <notations>
          <articulations>
            <breath-mark/>
            </articulations>
          </notations>
        <lyric number="1">
          <syllabic>end</syllabic>
          <text>ve</text>
          </lyric>
        </note>
      <note default-x="470.43" default-y="-15.00">
        <pitch>
          <step>C</step>
          <octave>4</octave>
          </pitch>
        <duration>1</duration>
        <voice>1</voice>
        <type>quarter</type>
        <stem>none</stem>
        <lyric number="1">
          <syllabic>begin</syllabic>
          <text>pec</text>
          </lyric>
        </note>
      <note default-x="497.84" default-y="-20.00">
        <pitch>
          <step>B</step>
          <alter>-1</alter>
          <octave>3</octave>
          </pitch>
        <duration>1</duration>
        <voice>1</voice>
        <type>quarter</type>
        <stem>none</stem>
        <lyric number="1">
          <syllabic>middle</syllabic>
          <text>ca</text>
          </lyric>
        </note>
      <note default-x="521.18" default-y="-15.00">
        <pitch>
          <step>C</step>
          <octave>4</octave>
          </pitch>
        <duration>1</duration>
        <voice>1</voice>
        <type>quarter</type>
        <stem>none</stem>
        <notations>
          <slur type="start" number="1"/>
          </notations>
        <lyric number="1">
          <syllabic>middle</syllabic>
          <text>to</text>
          </lyric>
        </note>
      <note default-x="544.52" default-y="-10.00">
        <pitch>
          <step>D</step>
          <octave>4</octave>
          </pitch>
        <duration>1</duration>
        <voice>1</voice>
        <type>quarter</type>
        <stem>none</stem>
        </note>
      <note default-x="567.86" default-y="-15.00">
        <pitch>
          <step>C</step>
          <octave>4</octave>
          </pitch>
        <duration>1</duration>
        <voice>1</voice>
        <type>quarter</type>
        <stem>none</stem>
        <notations>
          <slur type="stop" number="1"/>
          </notations>
        </note>
      <note default-x="594.66" default-y="-35.00">
        <pitch>
          <step>F</step>
          <octave>3</octave>
          </pitch>
        <duration>1</duration>
        <voice>1</voice>
        <type>quarter</type>
        <stem>none</stem>
        <notations>
          <slur type="start" number="1"/>
          </notations>
        <lyric number="1">
          <syllabic>end</syllabic>
          <text>rum</text>
          </lyric>
        </note>
      <note default-x="621.46" default-y="-30.00">
        <pitch>
          <step>G</step>
          <octave>3</octave>
          </pitch>
        <duration>1</duration>
        <voice>1</voice>
        <type>quarter</type>
        <stem>none</stem>
        </note>
      <note default-x="644.80" default-y="-25.00">
        <pitch>
          <step>A</step>
          <octave>3</octave>
          </pitch>
        <duration>1</duration>
        <voice>1</voice>
        <type>quarter</type>
        <stem>none</stem>
        </note>
      <note default-x="668.14" default-y="-30.00">
        <pitch>
          <step>G</step>
          <octave>3</octave>
          </pitch>
        <duration>1</duration>
        <voice>1</voice>
        <type>quarter</type>
        <stem>none</stem>
        </note>
      <note default-x="691.48" default-y="-25.00">
        <pitch>
          <step>A</step>
          <octave>3</octave>
          </pitch>
        <duration>1</duration>
        <voice>1</voice>
        <type>quarter</type>
        <stem>none</stem>
        <notations>
          <slur type="stop" number="1"/>
          <articulations>
            <breath-mark/>
            </articulations>
          </notations>
        </note>
      <note default-x="731.81" default-y="-20.00">
        <pitch>
          <step>B</step>
          <alter>-1</alter>
          <octave>3</octave>
          </pitch>
        <duration>1</duration>
        <voice>1</voice>
        <type>quarter</type>
        <stem>none</stem>
        <notations>
          <slur type="start" number="1"/>
          </notations>
        <lyric number="1">
          <syllabic>begin</syllabic>
          <text>mi</text>
          </lyric>
        </note>
      <note default-x="755.53" default-y="-25.00">
        <pitch>
          <step>A</step>
          <octave>3</octave>
          </pitch>
        <duration>1</duration>
        <voice>1</voice>
        <type>quarter</type>
        <stem>none</stem>
        <notations>
          <slur type="stop" number="1"/>
          </notations>
        </note>
      <note default-x="778.87" default-y="-30.00">
        <pitch>
          <step>G</step>
          <octave>3</octave>
          </pitch>
        <duration>1</duration>
        <voice>1</voice>
        <type>quarter</type>
        <stem>none</stem>
        <notations>
          <slur type="start" number="1"/>
          </notations>
        <lyric number="1">
          <syllabic>middle</syllabic>
          <text>se</text>
          </lyric>
        </note>
      <note default-x="802.21" default-y="-35.00">
        <pitch>
          <step>F</step>
          <octave>3</octave>
          </pitch>
        <duration>1</duration>
        <voice>1</voice>
        <type>quarter</type>
        <stem>none</stem>
        <notations>
          <slur type="stop" number="1"/>
          </notations>
        </note>
      <note default-x="825.55" default-y="-45.00">
        <pitch>
          <step>D</step>
          <octave>3</octave>
          </pitch>
        <duration>1</duration>
        <voice>1</voice>
        <type>quarter</type>
        <stem>none</stem>
        <notations>
          <slur type="start" number="1"/>
          </notations>
        <lyric number="1">
          <syllabic>middle</syllabic>
          <text>re</text>
          </lyric>
        </note>
      <note default-x="848.89" default-y="-35.00">
        <pitch>
          <step>F</step>
          <octave>3</octave>
          </pitch>
        <duration>1</duration>
        <voice>1</voice>
        <type>quarter</type>
        <stem>none</stem>
        </note>
      <note default-x="872.23" default-y="-30.00">
        <pitch>
          <step>G</step>
          <octave>3</octave>
          </pitch>
        <duration>1</duration>
        <voice>1</voice>
        <type>quarter</type>
        <stem>none</stem>
        </note>
      <note default-x="895.57" default-y="-35.00">
        <pitch>
          <step>F</step>
          <octave>3</octave>
          </pitch>
        <duration>1</duration>
        <voice>1</voice>
        <type>quarter</type>
        <stem>none</stem>
        <notations>
          <slur type="stop" number="1"/>
          </notations>
        </note>
      <note default-x="918.90" default-y="-35.00">
        <pitch>
          <step>F</step>
          <octave>3</octave>
          </pitch>
        <duration>1</duration>
        <voice>1</voice>
        <type>quarter</type>
        <stem>none</stem>
        <notations>
          <articulations>
            <caesura/>
            </articulations>
          </notations>
        <lyric number="1">
          <syllabic>end</syllabic>
          <text>re.</text>
          </lyric>
        </note>
      <note default-x="957.36" default-y="0.00">
        <pitch>
          <step>F</step>
          <octave>4</octave>
          </pitch>
        <duration>1</duration>
        <voice>1</voice>
        <type>quarter</type>
        <stem>none</stem>
        <lyric number="1">
          <syllabic>single</syllabic>
          <text>E</text>
          </lyric>
        </note>
      <note default-x="980.70" default-y="0.00">
        <pitch>
          <step>F</step>
          <octave>4</octave>
          </pitch>
        <duration>1</duration>
        <voice>1</voice>
        <type>quarter</type>
        <stem>none</stem>
        <lyric number="1">
          <syllabic>single</syllabic>
          <text>u</text>
          </lyric>
        </note>
      <note default-x="1004.04" default-y="5.00">
        <pitch>
          <step>G</step>
          <octave>4</octave>
          </pitch>
        <duration>1</duration>
        <voice>1</voice>
        <type>quarter</type>
        <stem>none</stem>
        <lyric number="1">
          <syllabic>single</syllabic>
          <text>o</text>
          </lyric>
        </note>
      <note default-x="1027.38" default-y="-5.00">
        <pitch>
          <step>E</step>
          <octave>4</octave>
          </pitch>
        <duration>1</duration>
        <voice>1</voice>
        <type>quarter</type>
        <stem>none</stem>
        <lyric number="1">
          <syllabic>single</syllabic>
          <text>u</text>
          </lyric>
        </note>
      <note default-x="1050.72" default-y="0.00">
        <pitch>
          <step>F</step>
          <octave>4</octave>
          </pitch>
        <duration>1</duration>
        <voice>1</voice>
        <type>quarter</type>
        <stem>none</stem>
        <lyric number="1">
          <syllabic>single</syllabic>
          <text>a</text>
          </lyric>
        </note>
      <note default-x="1074.06" default-y="-10.00">
        <pitch>
          <step>D</step>
          <octave>4</octave>
          </pitch>
        <duration>1</duration>
        <voice>1</voice>
        <type>quarter</type>
        <stem>none</stem>
        <lyric number="1">
          <syllabic>single</syllabic>
          <text>e.</text>
          </lyric>
        </note>
      <barline location="right">
        <bar-style>light-heavy</bar-style>
        </barline>
      </measure>
    </part>
  </score-partwise>
