<?xml version="1.0" encoding="UTF-8"?>
<!DOCTYPE score-partwise PUBLIC "-//Recordare//DTD MusicXML 3.0 Partwise//EN" "http://www.musicxml.org/dtds/partwise.dtd">
<score-partwise>
  <work>
    <work-title>Alma Redemptoris Mater</work-title>
    </work>
  <identification>
    <creator type="composer">Anonymous</creator>
    <encoding>
      <software>MuseScore 2.0.2</software>
      <encoding-date>2016-02-26</encoding-date>
      <supports element="accidental" type="yes"/>
      <supports element="beam" type="yes"/>
      <supports element="print" attribute="new-page" type="yes" value="yes"/>
      <supports element="print" attribute="new-system" type="yes" value="yes"/>
      <supports element="stem" type="yes"/>
      </encoding>
    </identification>
  <defaults>
    <scaling>
      <millimeters>7.05556</millimeters>
      <tenths>40</tenths>
      </scaling>
    <page-layout>
      <page-height>1584</page-height>
      <page-width>1224</page-width>
      <page-margins type="even">
        <left-margin>56.6929</left-margin>
        <right-margin>56.6929</right-margin>
        <top-margin>56.6929</top-margin>
        <bottom-margin>113.386</bottom-margin>
        </page-margins>
      <page-margins type="odd">
        <left-margin>56.6929</left-margin>
        <right-margin>56.6929</right-margin>
        <top-margin>56.6929</top-margin>
        <bottom-margin>113.386</bottom-margin>
        </page-margins>
      </page-layout>
    <word-font font-family="FreeSerif" font-size="10"/>
    <lyric-font font-family="FreeSerif" font-size="11"/>
    </defaults>
  <credit page="1">
    <credit-words default-x="1167.31" default-y="1402.31" justify="right" valign="bottom" font-size="12">Anonymous</credit-words>
    </credit>
  <credit page="1">
    <credit-words default-x="612" default-y="1527.31" justify="center" valign="top" font-size="24">Kyrie</credit-words>
    </credit>
  <part-list>
    <score-part id="P1">
      <part-name>Piano</part-name>
      <part-abbreviation>Pno.</part-abbreviation>
      <score-instrument id="P1-I1">
        <instrument-name>Piano</instrument-name>
        </score-instrument>
      <midi-device id="P1-I1" port="1"></midi-device>
      <midi-instrument id="P1-I1">
        <midi-channel>1</midi-channel>
        <midi-program>1</midi-program>
        <volume>78.7402</volume>
        <pan>0</pan>
        </midi-instrument>
      </score-part>
    </part-list>
  <part id="P1">
    <measure number="1" width="1110.61">
      <print>
        <system-layout>
          <system-margins>
            <left-margin>0.00</left-margin>
            <right-margin>0.00</right-margin>
            </system-margins>
          <top-system-distance>195.00</top-system-distance>
          </system-layout>
        </print>
      <attributes>
        <divisions>1</divisions>
        <key>
          <fifths>0</fifths>
          <mode>none</mode>
          </key>
        <time>
          <beats>63</beats>
          <beat-type>4</beat-type>
          </time>
        <clef>
          <sign>C</sign>
          <line>3</line>
          </clef>
        </attributes>
      <note default-x="89.94" default-y="-30.00">
        <pitch>
          <step>A</step>
          <octave>3</octave>
          </pitch>
        <duration>1</duration>
        <voice>1</voice>
        <type>quarter</type>
        <stem>none</stem>
        <notations>
          <slur type="start" number="1"/>
          </notations>
        <lyric number="1">
          <syllabic>begin</syllabic>
          <text>Ky</text>
          </lyric>
        </note>
      <note default-x="118.77" default-y="-20.00">
        <pitch>
          <step>C</step>
          <octave>4</octave>
          </pitch>
        <duration>1</duration>
        <voice>1</voice>
        <type>quarter</type>
        <stem>none</stem>
        <notations>
          <slur type="stop" number="1"/>
          </notations>
        </note>
      <note default-x="147.59" default-y="-15.00">
        <pitch>
          <step>D</step>
          <octave>4</octave>
          </pitch>
        <duration>1</duration>
        <voice>1</voice>
        <type>quarter</type>
        <stem>none</stem>
        <notations>
          <slur type="start" number="1"/>
          </notations>
        </note>
      <note default-x="176.41" default-y="-10.00">
        <pitch>
          <step>E</step>
          <octave>4</octave>
          </pitch>
        <duration>1</duration>
        <voice>1</voice>
        <type>quarter</type>
        <stem>none</stem>
        <notations>
          <slur type="stop" number="1"/>
          </notations>
        </note>
      <note default-x="205.23" default-y="-15.00">
        <pitch>
          <step>D</step>
          <octave>4</octave>
          </pitch>
        <duration>1</duration>
        <voice>1</voice>
        <type>quarter</type>
        <stem>none</stem>
        <notations>
          <slur type="start" number="1"/>
          </notations>
        <lyric number="1">
          <syllabic>middle</syllabic>
          <text>ri</text>
          </lyric>
        </note>
      <note default-x="234.06" default-y="-20.00">
        <pitch>
          <step>C</step>
          <octave>4</octave>
          </pitch>
        <duration>1</duration>
        <voice>1</voice>
        <type>quarter</type>
        <stem>none</stem>
        <notations>
          <slur type="stop" number="1"/>
          </notations>
        </note>
      <note default-x="262.88" default-y="-25.00">
        <pitch>
          <step>B</step>
          <octave>3</octave>
          </pitch>
        <duration>1</duration>
        <voice>1</voice>
        <type>quarter</type>
        <stem>none</stem>
        <notations>
          <slur type="start" number="1"/>
          </notations>
        <lyric number="1">
          <syllabic>end</syllabic>
          <text>e</text>
          </lyric>
        </note>
      <note default-x="291.70" default-y="-30.00">
        <pitch>
          <step>A</step>
          <octave>3</octave>
          </pitch>
        <duration>1</duration>
        <voice>1</voice>
        <type>quarter</type>
        <stem>none</stem>
        </note>
      <note default-x="320.52" default-y="-20.00">
        <pitch>
          <step>C</step>
          <octave>4</octave>
          </pitch>
        <duration>1</duration>
        <voice>1</voice>
        <type>quarter</type>
        <stem>none</stem>
        </note>
      <note default-x="349.35" default-y="-30.00">
        <pitch>
          <step>A</step>
          <octave>3</octave>
          </pitch>
        <duration>1</duration>
        <voice>1</voice>
        <type>quarter</type>
        <stem>none</stem>
        </note>
      <note default-x="378.17" default-y="-35.00">
        <pitch>
          <step>G</step>
          <octave>3</octave>
          </pitch>
        <duration>1</duration>
        <voice>1</voice>
        <type>quarter</type>
        <stem>none</stem>
        </note>
      <note default-x="406.99" default-y="-30.00">
        <pitch>
          <step>A</step>
          <octave>3</octave>
          </pitch>
        <duration>1</duration>
        <voice>1</voice>
        <type>quarter</type>
        <stem>none</stem>
        </note>
      <note default-x="435.81" default-y="-35.00">
        <pitch>
          <step>G</step>
          <octave>3</octave>
          </pitch>
        <duration>1</duration>
        <voice>1</voice>
        <type>quarter</type>
        <stem>none</stem>
        <notations>
          <slur type="stop" number="1"/>
          </notations>
        </note>
      <note default-x="464.64" default-y="-30.00">
        <pitch>
          <step>A</step>
          <octave>3</octave>
          </pitch>
        <duration>1</duration>
        <voice>1</voice>
        <type>quarter</type>
        <stem>none</stem>
        <lyric number="1">
          <syllabic>begin</syllabic>
          <text>e</text>
          </lyric>
        </note>
      <note default-x="493.46" default-y="-20.00">
        <pitch>
          <step>C</step>
          <octave>4</octave>
          </pitch>
        <duration>1</duration>
        <voice>1</voice>
        <type>quarter</type>
        <stem>none</stem>
        <lyric number="1">
          <syllabic>middle</syllabic>
          <text>le</text>
          </lyric>
        </note>
      <note default-x="522.28" default-y="-15.00">
        <pitch>
          <step>D</step>
          <octave>4</octave>
          </pitch>
        <duration>1</duration>
        <voice>1</voice>
        <type>quarter</type>
        <stem>none</stem>
        <lyric number="1">
          <syllabic>middle</syllabic>
          <text>i</text>
          </lyric>
        </note>
      <note default-x="551.10" default-y="-25.00">
        <pitch>
          <step>B</step>
          <octave>3</octave>
          </pitch>
        <duration>1</duration>
        <voice>1</voice>
        <type>quarter</type>
        <stem>none</stem>
        <notations>
          <slur type="start" number="1"/>
          </notations>
        <lyric number="1">
          <syllabic>end</syllabic>
          <text>son.</text>
          </lyric>
        </note>
      <note default-x="579.93" default-y="-30.00">
        <pitch>
          <step>A</step>
          <octave>3</octave>
          </pitch>
        <duration>1</duration>
        <voice>1</voice>
        <type>quarter</type>
        <stem>none</stem>
        <notations>
          <slur type="stop" number="1"/>
          <articulations>
            <caesura/>
            </articulations>
          </notations>
        </note>
      <note default-x="630.13" default-y="-45.00">
        <pitch>
          <step>E</step>
          <octave>3</octave>
          </pitch>
        <duration>1</duration>
        <voice>1</voice>
        <type>quarter</type>
        <stem>none</stem>
        <lyric number="1">
          <syllabic>begin</syllabic>
          <text>Ky</text>
          </lyric>
        </note>
      <note default-x="658.96" default-y="-35.00">
        <pitch>
          <step>G</step>
          <octave>3</octave>
          </pitch>
        <duration>1</duration>
        <voice>1</voice>
        <type>quarter</type>
        <stem>none</stem>
        <notations>
          <slur type="start" number="1"/>
          </notations>
        <lyric number="1">
          <syllabic>middle</syllabic>
          <text>ri</text>
          </lyric>
        </note>
      <note default-x="687.78" default-y="-30.00">
        <pitch>
          <step>A</step>
          <octave>3</octave>
          </pitch>
        <duration>1</duration>
        <voice>1</voice>
        <type>quarter</type>
        <stem>none</stem>
        <notations>
          <slur type="stop" number="1"/>
          </notations>
        </note>
      <note default-x="716.60" default-y="-30.00">
        <pitch>
          <step>A</step>
          <octave>3</octave>
          </pitch>
        <duration>1</duration>
        <voice>1</voice>
        <type>quarter</type>
        <stem>none</stem>
        <notations>
          <slur type="start" number="1"/>
          </notations>
        <lyric number="1">
          <syllabic>end</syllabic>
          <text>e</text>
          </lyric>
        </note>
      <note default-x="745.42" default-y="-35.00">
        <pitch>
          <step>G</step>
          <octave>3</octave>
          </pitch>
        <duration>1</duration>
        <voice>1</voice>
        <type>quarter</type>
        <stem>none</stem>
        </note>
      <note default-x="774.25" default-y="-30.00">
        <pitch>
          <step>A</step>
          <octave>3</octave>
          </pitch>
        <duration>1</duration>
        <voice>1</voice>
        <type>quarter</type>
        <stem>none</stem>
        <notations>
          <slur type="stop" number="1"/>
          </notations>
        </note>
      <note default-x="803.07" default-y="-30.00">
        <pitch>
          <step>A</step>
          <octave>3</octave>
          </pitch>
        <duration>1</duration>
        <voice>1</voice>
        <type>quarter</type>
        <stem>none</stem>
        <notations>
          <slur type="start" number="1"/>
          </notations>
        </note>
      <note default-x="831.89" default-y="-35.00">
        <pitch>
          <step>G</step>
          <octave>3</octave>
          </pitch>
        <duration>1</duration>
        <voice>1</voice>
        <type>quarter</type>
        <stem>none</stem>
        <notations>
          <slur type="stop" number="1"/>
          </notations>
        </note>
      <note default-x="860.71" default-y="-30.00">
        <pitch>
          <step>A</step>
          <octave>3</octave>
          </pitch>
        <duration>1</duration>
        <voice>1</voice>
        <type>quarter</type>
        <stem>none</stem>
        <notations>
          <slur type="start" number="1"/>
          </notations>
        </note>
      <note default-x="889.54" default-y="-35.00">
        <pitch>
          <step>G</step>
          <octave>3</octave>
          </pitch>
        <duration>1</duration>
        <voice>1</voice>
        <type>quarter</type>
        <stem>none</stem>
        <notations>
          <slur type="stop" number="1"/>
          </notations>
        </note>
      <note default-x="918.36" default-y="-30.00">
        <pitch>
          <step>A</step>
          <octave>3</octave>
          </pitch>
        <duration>1</duration>
        <voice>1</voice>
        <type>quarter</type>
        <stem>none</stem>
        <lyric number="1">
          <syllabic>begin</syllabic>
          <text>e</text>
          </lyric>
        </note>
      <note default-x="947.18" default-y="-20.00">
        <pitch>
          <step>C</step>
          <octave>4</octave>
          </pitch>
        <duration>1</duration>
        <voice>1</voice>
        <type>quarter</type>
        <stem>none</stem>
        <lyric number="1">
          <syllabic>middle</syllabic>
          <text>le</text>
          </lyric>
        </note>
      <note default-x="976.00" default-y="-15.00">
        <pitch>
          <step>D</step>
          <octave>4</octave>
          </pitch>
        <duration>1</duration>
        <voice>1</voice>
        <type>quarter</type>
        <stem>none</stem>
        <lyric number="1">
          <syllabic>middle</syllabic>
          <text>i</text>
          </lyric>
        </note>
      <note default-x="1004.83" default-y="-25.00">
        <pitch>
          <step>B</step>
          <octave>3</octave>
          </pitch>
        <duration>1</duration>
        <voice>1</voice>
        <type>quarter</type>
        <stem>none</stem>
        <notations>
          <slur type="start" number="1"/>
          </notations>
        <lyric number="1">
          <syllabic>end</syllabic>
          <text>son.</text>
          </lyric>
        </note>
      <direction placement="above">
        <direction-type>
          <words>Tertium
</words>
          <words>ut primus</words>
          </direction-type>
        </direction>
      <note default-x="1033.65" default-y="-30.00">
        <pitch>
          <step>A</step>
          <octave>3</octave>
          </pitch>
        <duration>1</duration>
        <voice>1</voice>
        <type>quarter</type>
        <stem>none</stem>
        <notations>
          <slur type="stop" number="1"/>
          <articulations>
            <caesura/>
            </articulations>
          </notations>
        </note>
      </measure>
    <measure number="2" width="1110.61">
      <print new-system="yes">
        <system-layout>
          <system-margins>
            <left-margin>0.00</left-margin>
            <right-margin>0.00</right-margin>
            </system-margins>
          <system-distance>150.00</system-distance>
          </system-layout>
        </print>
      <note default-x="76.17" default-y="-20.00">
        <pitch>
          <step>E</step>
          <octave>4</octave>
          </pitch>
        <duration>1</duration>
        <voice>1</voice>
        <type>quarter</type>
        <stem>none</stem>
        <lyric number="1">
          <syllabic>begin</syllabic>
          <text>Chri</text>
          </lyric>
        </note>
      <note default-x="110.14" default-y="-20.00">
        <pitch>
          <step>E</step>
          <octave>4</octave>
          </pitch>
        <duration>1</duration>
        <voice>1</voice>
        <type>quarter</type>
        <stem>none</stem>
        <notations>
          <slur type="start" number="1"/>
          </notations>
        <lyric number="1">
          <syllabic>end</syllabic>
          <text>ste</text>
          </lyric>
        </note>
      <note default-x="144.10" default-y="-25.00">
        <pitch>
          <step>D</step>
          <octave>4</octave>
          </pitch>
        <duration>1</duration>
        <voice>1</voice>
        <type>quarter</type>
        <stem>none</stem>
        </note>
      <note default-x="178.07" default-y="-15.00">
        <pitch>
          <step>F</step>
          <octave>4</octave>
          </pitch>
        <duration>1</duration>
        <voice>1</voice>
        <type>quarter</type>
        <stem>none</stem>
        </note>
      <note default-x="212.03" default-y="-20.00">
        <pitch>
          <step>E</step>
          <octave>4</octave>
          </pitch>
        <duration>1</duration>
        <voice>1</voice>
        <type>quarter</type>
        <stem>none</stem>
        </note>
      <note default-x="246.00" default-y="-25.00">
        <pitch>
          <step>D</step>
          <octave>4</octave>
          </pitch>
        <duration>1</duration>
        <voice>1</voice>
        <type>quarter</type>
        <stem>none</stem>
        <notations>
          <slur type="stop" number="1"/>
          </notations>
        </note>
      <note default-x="279.97" default-y="-25.00">
        <pitch>
          <step>D</step>
          <octave>4</octave>
          </pitch>
        <duration>1</duration>
        <voice>1</voice>
        <type>quarter</type>
        <stem>none</stem>
        <notations>
          <slur type="start" number="1"/>
          </notations>
        </note>
      <note default-x="313.93" default-y="-30.00">
        <pitch>
          <step>C</step>
          <octave>4</octave>
          </pitch>
        <duration>1</duration>
        <voice>1</voice>
        <type>quarter</type>
        <stem>none</stem>
        <notations>
          <slur type="stop" number="1"/>
          </notations>
        </note>
      <note default-x="347.90" default-y="-25.00">
        <pitch>
          <step>D</step>
          <octave>4</octave>
          </pitch>
        <duration>1</duration>
        <voice>1</voice>
        <type>quarter</type>
        <stem>none</stem>
        <lyric number="1">
          <syllabic>begin</syllabic>
          <text>e</text>
          </lyric>
        </note>
      <note default-x="381.86" default-y="-25.00">
        <pitch>
          <step>D</step>
          <octave>4</octave>
          </pitch>
        <duration>1</duration>
        <voice>1</voice>
        <type>quarter</type>
        <stem>none</stem>
        <lyric number="1">
          <syllabic>middle</syllabic>
          <text>le</text>
          </lyric>
        </note>
      <note default-x="415.83" default-y="-15.00">
        <pitch>
          <step>F</step>
          <octave>4</octave>
          </pitch>
        <duration>1</duration>
        <voice>1</voice>
        <type>quarter</type>
        <stem>none</stem>
        <lyric number="1">
          <syllabic>middle</syllabic>
          <text>i</text>
          </lyric>
        </note>
      <note default-x="449.79" default-y="-20.00">
        <pitch>
          <step>E</step>
          <octave>4</octave>
          </pitch>
        <duration>1</duration>
        <voice>1</voice>
        <type>quarter</type>
        <stem>none</stem>
        <notations>
          <articulations>
            <caesura/>
            </articulations>
          </notations>
        <lyric number="1">
          <syllabic>end</syllabic>
          <text>son.</text>
          </lyric>
        </note>
      <note default-x="500.76" default-y="-20.00">
        <pitch>
          <step>E</step>
          <octave>4</octave>
          </pitch>
        <duration>1</duration>
        <voice>1</voice>
        <type>quarter</type>
        <stem>none</stem>
        <notations>
          <slur type="start" number="1"/>
          </notations>
        <lyric number="1">
          <syllabic>begin</syllabic>
          <text>Chri</text>
          </lyric>
        </note>
      <note default-x="540.57" default-y="-25.00">
        <pitch>
          <step>D</step>
          <octave>4</octave>
          </pitch>
        <duration>1</duration>
        <voice>1</voice>
        <type>quarter</type>
        <stem>none</stem>
        </note>
      <note default-x="574.53" default-y="-30.00">
        <pitch>
          <step>C</step>
          <octave>4</octave>
          </pitch>
        <duration>1</duration>
        <voice>1</voice>
        <type>quarter</type>
        <stem>none</stem>
        </note>
      <note default-x="608.50" default-y="-25.00">
        <pitch>
          <step>D</step>
          <octave>4</octave>
          </pitch>
        <duration>1</duration>
        <voice>1</voice>
        <type>quarter</type>
        <stem>none</stem>
        </note>
      <note default-x="642.46" default-y="-30.00">
        <pitch>
          <step>C</step>
          <octave>4</octave>
          </pitch>
        <duration>1</duration>
        <voice>1</voice>
        <type>quarter</type>
        <stem>none</stem>
        <notations>
          <slur type="stop" number="1"/>
          </notations>
        </note>
      <note default-x="676.43" default-y="-35.00">
        <pitch>
          <step>B</step>
          <octave>3</octave>
          </pitch>
        <duration>1</duration>
        <voice>1</voice>
        <type>quarter</type>
        <stem>none</stem>
        <notations>
          <slur type="start" number="1"/>
          </notations>
        <lyric number="1">
          <syllabic>end</syllabic>
          <text>ste</text>
          </lyric>
        </note>
      <note default-x="710.40" default-y="-40.00">
        <pitch>
          <step>A</step>
          <octave>3</octave>
          </pitch>
        <duration>1</duration>
        <voice>1</voice>
        <type>quarter</type>
        <stem>none</stem>
        </note>
      <note default-x="744.36" default-y="-30.00">
        <pitch>
          <step>C</step>
          <octave>4</octave>
          </pitch>
        <duration>1</duration>
        <voice>1</voice>
        <type>quarter</type>
        <stem>none</stem>
        </note>
      <note default-x="778.33" default-y="-40.00">
        <pitch>
          <step>A</step>
          <octave>3</octave>
          </pitch>
        <duration>1</duration>
        <voice>1</voice>
        <type>quarter</type>
        <stem>none</stem>
        </note>
      <note default-x="812.29" default-y="-45.00">
        <pitch>
          <step>G</step>
          <octave>3</octave>
          </pitch>
        <duration>1</duration>
        <voice>1</voice>
        <type>quarter</type>
        <stem>none</stem>
        </note>
      <note default-x="846.26" default-y="-40.00">
        <pitch>
          <step>A</step>
          <octave>3</octave>
          </pitch>
        <duration>1</duration>
        <voice>1</voice>
        <type>quarter</type>
        <stem>none</stem>
        </note>
      <note default-x="880.22" default-y="-45.00">
        <pitch>
          <step>G</step>
          <octave>3</octave>
          </pitch>
        <duration>1</duration>
        <voice>1</voice>
        <type>quarter</type>
        <stem>none</stem>
        <notations>
          <slur type="stop" number="1"/>
          </notations>
        </note>
      <note default-x="914.19" default-y="-40.00">
        <pitch>
          <step>A</step>
          <octave>3</octave>
          </pitch>
        <duration>1</duration>
        <voice>1</voice>
        <type>quarter</type>
        <stem>none</stem>
        <lyric number="1">
          <syllabic>begin</syllabic>
          <text>e</text>
          </lyric>
        </note>
      <note default-x="948.15" default-y="-30.00">
        <pitch>
          <step>C</step>
          <octave>4</octave>
          </pitch>
        <duration>1</duration>
        <voice>1</voice>
        <type>quarter</type>
        <stem>none</stem>
        <lyric number="1">
          <syllabic>middle</syllabic>
          <text>le</text>
          </lyric>
        </note>
      <note default-x="982.12" default-y="-25.00">
        <pitch>
          <step>D</step>
          <octave>4</octave>
          </pitch>
        <duration>1</duration>
        <voice>1</voice>
        <type>quarter</type>
        <stem>none</stem>
        <lyric number="1">
          <syllabic>middle</syllabic>
          <text>i</text>
          </lyric>
        </note>
      <note default-x="1016.08" default-y="-35.00">
        <pitch>
          <step>B</step>
          <octave>3</octave>
          </pitch>
        <duration>1</duration>
        <voice>1</voice>
        <type>quarter</type>
        <stem>none</stem>
        <notations>
          <slur type="start" number="1"/>
          </notations>
        <lyric number="1">
          <syllabic>end</syllabic>
          <text>son.</text>
          </lyric>
        </note>
      <direction placement="above">
        <direction-type>
          <words>Tertium
</words>
          <words>ut primus</words>
          </direction-type>
        </direction>
      <note default-x="1050.05" default-y="-40.00">
        <pitch>
          <step>A</step>
          <octave>3</octave>
          </pitch>
        <duration>1</duration>
        <voice>1</voice>
        <type>quarter</type>
        <stem>none</stem>
        <notations>
          <slur type="stop" number="1"/>
          <articulations>
            <caesura/>
            </articulations>
          </notations>
        </note>
      </measure>
    <measure number="3" width="1110.61">
      <print new-system="yes">
        <system-layout>
          <system-margins>
            <left-margin>0.00</left-margin>
            <right-margin>0.00</right-margin>
            </system-margins>
          <system-distance>150.00</system-distance>
          </system-layout>
        </print>
      <note default-x="62.49" default-y="-20.00">
        <pitch>
          <step>E</step>
          <octave>4</octave>
          </pitch>
        <duration>1</duration>
        <voice>1</voice>
        <type>quarter</type>
        <stem>none</stem>
        <lyric number="1">
          <syllabic>begin</syllabic>
          <text>Ky</text>
          </lyric>
        </note>
      <note default-x="92.77" default-y="-10.00">
        <pitch>
          <step>G</step>
          <octave>4</octave>
          </pitch>
        <duration>1</duration>
        <voice>1</voice>
        <type>quarter</type>
        <stem>none</stem>
        <notations>
          <slur type="start" number="1"/>
          </notations>
        <lyric number="1">
          <syllabic>middle</syllabic>
          <text>ri</text>
          </lyric>
        </note>
      <note default-x="123.05" default-y="-5.00">
        <pitch>
          <step>A</step>
          <octave>4</octave>
          </pitch>
        <duration>1</duration>
        <voice>1</voice>
        <type>quarter</type>
        <stem>none</stem>
        <notations>
          <slur type="stop" number="1"/>
          </notations>
        </note>
      <note default-x="153.33" default-y="-5.00">
        <pitch>
          <step>A</step>
          <octave>4</octave>
          </pitch>
        <duration>1</duration>
        <voice>1</voice>
        <type>quarter</type>
        <stem>none</stem>
        <notations>
          <slur type="start" number="1"/>
          </notations>
        <lyric number="1">
          <syllabic>end</syllabic>
          <text>e</text>
          </lyric>
        </note>
      <note default-x="183.61" default-y="-10.00">
        <pitch>
          <step>G</step>
          <octave>4</octave>
          </pitch>
        <duration>1</duration>
        <voice>1</voice>
        <type>quarter</type>
        <stem>none</stem>
        </note>
      <note default-x="213.89" default-y="-5.00">
        <pitch>
          <step>A</step>
          <octave>4</octave>
          </pitch>
        <duration>1</duration>
        <voice>1</voice>
        <type>quarter</type>
        <stem>none</stem>
        <notations>
          <slur type="stop" number="1"/>
          </notations>
        </note>
      <note default-x="244.17" default-y="-20.00">
        <pitch>
          <step>E</step>
          <octave>4</octave>
          </pitch>
        <duration>1</duration>
        <voice>1</voice>
        <type>quarter</type>
        <stem>none</stem>
        <notations>
          <slur type="start" number="1"/>
          </notations>
        </note>
      <note default-x="274.45" default-y="-25.00">
        <pitch>
          <step>D</step>
          <octave>4</octave>
          </pitch>
        <duration>1</duration>
        <voice>1</voice>
        <type>quarter</type>
        <stem>none</stem>
        </note>
      <note default-x="304.73" default-y="-15.00">
        <pitch>
          <step>F</step>
          <octave>4</octave>
          </pitch>
        <duration>1</duration>
        <voice>1</voice>
        <type>quarter</type>
        <stem>none</stem>
        </note>
      <note default-x="335.01" default-y="-20.00">
        <pitch>
          <step>E</step>
          <octave>4</octave>
          </pitch>
        <duration>1</duration>
        <voice>1</voice>
        <type>quarter</type>
        <stem>none</stem>
        </note>
      <note default-x="365.29" default-y="-25.00">
        <pitch>
          <step>D</step>
          <octave>4</octave>
          </pitch>
        <duration>1</duration>
        <voice>1</voice>
        <type>quarter</type>
        <stem>none</stem>
        <notations>
          <slur type="stop" number="1"/>
          </notations>
        </note>
      <note default-x="395.57" default-y="-25.00">
        <pitch>
          <step>D</step>
          <octave>4</octave>
          </pitch>
        <duration>1</duration>
        <voice>1</voice>
        <type>quarter</type>
        <stem>none</stem>
        <notations>
          <slur type="start" number="1"/>
          </notations>
        </note>
      <note default-x="425.85" default-y="-30.00">
        <pitch>
          <step>C</step>
          <octave>4</octave>
          </pitch>
        <duration>1</duration>
        <voice>1</voice>
        <type>quarter</type>
        <stem>none</stem>
        <notations>
          <slur type="stop" number="1"/>
          </notations>
        </note>
      <note default-x="456.13" default-y="-25.00">
        <pitch>
          <step>D</step>
          <octave>4</octave>
          </pitch>
        <duration>1</duration>
        <voice>1</voice>
        <type>quarter</type>
        <stem>none</stem>
        <lyric number="1">
          <syllabic>begin</syllabic>
          <text>e</text>
          </lyric>
        </note>
      <note default-x="486.41" default-y="-25.00">
        <pitch>
          <step>D</step>
          <octave>4</octave>
          </pitch>
        <duration>1</duration>
        <voice>1</voice>
        <type>quarter</type>
        <stem>none</stem>
        <lyric number="1">
          <syllabic>middle</syllabic>
          <text>le</text>
          </lyric>
        </note>
      <note default-x="516.69" default-y="-15.00">
        <pitch>
          <step>F</step>
          <octave>4</octave>
          </pitch>
        <duration>1</duration>
        <voice>1</voice>
        <type>quarter</type>
        <stem>none</stem>
        <lyric number="1">
          <syllabic>middle</syllabic>
          <text>i</text>
          </lyric>
        </note>
      <note default-x="546.97" default-y="-20.00">
        <pitch>
          <step>E</step>
          <octave>4</octave>
          </pitch>
        <duration>1</duration>
        <voice>1</voice>
        <type>quarter</type>
        <stem>none</stem>
        <notations>
          <articulations>
            <caesura/>
            </articulations>
          </notations>
        <lyric number="1">
          <syllabic>end</syllabic>
          <text>son.</text>
          </lyric>
        </note>
      <note default-x="594.25" default-y="-20.00">
        <pitch>
          <step>E</step>
          <octave>4</octave>
          </pitch>
        <duration>1</duration>
        <voice>1</voice>
        <type>quarter</type>
        <stem>none</stem>
        <notations>
          <slur type="start" number="1"/>
          </notations>
        <lyric number="1">
          <syllabic>begin</syllabic>
          <text>Ky</text>
          </lyric>
        </note>
      <note default-x="624.53" default-y="-25.00">
        <pitch>
          <step>D</step>
          <octave>4</octave>
          </pitch>
        <duration>1</duration>
        <voice>1</voice>
        <type>quarter</type>
        <stem>none</stem>
        </note>
      <note default-x="654.81" default-y="-30.00">
        <pitch>
          <step>C</step>
          <octave>4</octave>
          </pitch>
        <duration>1</duration>
        <voice>1</voice>
        <type>quarter</type>
        <stem>none</stem>
        </note>
      <note default-x="685.09" default-y="-25.00">
        <pitch>
          <step>D</step>
          <octave>4</octave>
          </pitch>
        <duration>1</duration>
        <voice>1</voice>
        <type>quarter</type>
        <stem>none</stem>
        <notations>
          <slur type="stop" number="1"/>
          </notations>
        </note>
      <note default-x="715.37" default-y="-30.00">
        <pitch>
          <step>C</step>
          <octave>4</octave>
          </pitch>
        <duration>1</duration>
        <voice>1</voice>
        <type>quarter</type>
        <stem>none</stem>
        <lyric number="1">
          <syllabic>middle</syllabic>
          <text>ri</text>
          </lyric>
        </note>
      <note default-x="745.65" default-y="-35.00">
        <pitch>
          <step>B</step>
          <octave>3</octave>
          </pitch>
        <duration>1</duration>
        <voice>1</voice>
        <type>quarter</type>
        <stem>none</stem>
        <notations>
          <slur type="start" number="1"/>
          </notations>
        <lyric number="1">
          <syllabic>end</syllabic>
          <text>e</text>
          </lyric>
        </note>
      <note default-x="775.93" default-y="-40.00">
        <pitch>
          <step>A</step>
          <octave>3</octave>
          </pitch>
        <duration>1</duration>
        <voice>1</voice>
        <type>quarter</type>
        <stem>none</stem>
        </note>
      <note default-x="806.21" default-y="-30.00">
        <pitch>
          <step>C</step>
          <octave>4</octave>
          </pitch>
        <duration>1</duration>
        <voice>1</voice>
        <type>quarter</type>
        <stem>none</stem>
        </note>
      <note default-x="836.49" default-y="-40.00">
        <pitch>
          <step>A</step>
          <octave>3</octave>
          </pitch>
        <duration>1</duration>
        <voice>1</voice>
        <type>quarter</type>
        <stem>none</stem>
        </note>
      <note default-x="866.77" default-y="-45.00">
        <pitch>
          <step>G</step>
          <octave>3</octave>
          </pitch>
        <duration>1</duration>
        <voice>1</voice>
        <type>quarter</type>
        <stem>none</stem>
        </note>
      <note default-x="897.05" default-y="-40.00">
        <pitch>
          <step>A</step>
          <octave>3</octave>
          </pitch>
        <duration>1</duration>
        <voice>1</voice>
        <type>quarter</type>
        <stem>none</stem>
        </note>
      <note default-x="927.33" default-y="-45.00">
        <pitch>
          <step>G</step>
          <octave>3</octave>
          </pitch>
        <duration>1</duration>
        <voice>1</voice>
        <type>quarter</type>
        <stem>none</stem>
        <notations>
          <slur type="stop" number="1"/>
          </notations>
        </note>
      <note default-x="957.61" default-y="-40.00">
        <pitch>
          <step>A</step>
          <octave>3</octave>
          </pitch>
        <duration>1</duration>
        <voice>1</voice>
        <type>quarter</type>
        <stem>none</stem>
        <lyric number="1">
          <syllabic>begin</syllabic>
          <text>e</text>
          </lyric>
        </note>
      <note default-x="987.89" default-y="-30.00">
        <pitch>
          <step>C</step>
          <octave>4</octave>
          </pitch>
        <duration>1</duration>
        <voice>1</voice>
        <type>quarter</type>
        <stem>none</stem>
        <lyric number="1">
          <syllabic>middle</syllabic>
          <text>le</text>
          </lyric>
        </note>
      <note default-x="1018.17" default-y="-25.00">
        <pitch>
          <step>D</step>
          <octave>4</octave>
          </pitch>
        <duration>1</duration>
        <voice>1</voice>
        <type>quarter</type>
        <stem>none</stem>
        <lyric number="1">
          <syllabic>middle</syllabic>
          <text>i</text>
          </lyric>
        </note>
      <note default-x="1048.45" default-y="-35.00">
        <pitch>
          <step>B</step>
          <octave>3</octave>
          </pitch>
        <duration>1</duration>
        <voice>1</voice>
        <type>quarter</type>
        <stem>none</stem>
        <notations>
          <slur type="start" number="1"/>
          </notations>
        <lyric number="1">
          <syllabic>end</syllabic>
          <text>son.</text>
          </lyric>
        </note>
      <note default-x="1078.73" default-y="-40.00">
        <pitch>
          <step>A</step>
          <octave>3</octave>
          </pitch>
        <duration>1</duration>
        <voice>1</voice>
        <type>quarter</type>
        <stem>none</stem>
        <notations>
          <slur type="stop" number="1"/>
          </notations>
        </note>
      </measure>
    <measure number="4" width="1110.61">
      <print new-system="yes">
        <system-layout>
          <system-margins>
            <left-margin>0.00</left-margin>
            <right-margin>0.00</right-margin>
            </system-margins>
          <system-distance>150.00</system-distance>
          </system-layout>
        </print>
      <note default-x="89.17" default-y="-20.00">
        <pitch>
          <step>E</step>
          <octave>4</octave>
          </pitch>
        <duration>1</duration>
        <voice>1</voice>
        <type>quarter</type>
        <stem>none</stem>
        <lyric number="1">
          <syllabic>begin</syllabic>
          <text>Chri</text>
          </lyric>
        </note>
      <note default-x="110.27" default-y="-10.00">
        <pitch>
          <step>G</step>
          <octave>4</octave>
          </pitch>
        <duration>1</duration>
        <voice>1</voice>
        <type>quarter</type>
        <stem>none</stem>
        <notations>
          <slur type="start" number="1"/>
          </notations>
        <lyric number="1">
          <syllabic>end</syllabic>
          <text>ste</text>
          </lyric>
        </note>
      <note default-x="131.37" default-y="-5.00">
        <pitch>
          <step>A</step>
          <octave>4</octave>
          </pitch>
        <duration>1</duration>
        <voice>1</voice>
        <type>quarter</type>
        <stem>none</stem>
        <notations>
          <slur type="stop" number="1"/>
          </notations>
        </note>
      <note default-x="151.61" default-y="-5.00">
        <pitch>
          <step>A</step>
          <octave>4</octave>
          </pitch>
        <duration>1</duration>
        <voice>1</voice>
        <type>quarter</type>
        <stem>none</stem>
        <notations>
          <slur type="start" number="1"/>
          </notations>
        </note>
      <note default-x="171.84" default-y="-10.00">
        <pitch>
          <step>G</step>
          <octave>4</octave>
          </pitch>
        <duration>1</duration>
        <voice>1</voice>
        <type>quarter</type>
        <stem>none</stem>
        </note>
      <note default-x="192.08" default-y="-5.00">
        <pitch>
          <step>A</step>
          <octave>4</octave>
          </pitch>
        <duration>1</duration>
        <voice>1</voice>
        <type>quarter</type>
        <stem>none</stem>
        </note>
      <note default-x="212.31" default-y="-20.00">
        <pitch>
          <step>E</step>
          <octave>4</octave>
          </pitch>
        <duration>1</duration>
        <voice>1</voice>
        <type>quarter</type>
        <stem>none</stem>
        </note>
      <note default-x="232.55" default-y="-25.00">
        <pitch>
          <step>D</step>
          <octave>4</octave>
          </pitch>
        <duration>1</duration>
        <voice>1</voice>
        <type>quarter</type>
        <stem>none</stem>
        </note>
      <note default-x="252.79" default-y="-15.00">
        <pitch>
          <step>F</step>
          <octave>4</octave>
          </pitch>
        <duration>1</duration>
        <voice>1</voice>
        <type>quarter</type>
        <stem>none</stem>
        </note>
      <note default-x="273.02" default-y="-20.00">
        <pitch>
          <step>E</step>
          <octave>4</octave>
          </pitch>
        <duration>1</duration>
        <voice>1</voice>
        <type>quarter</type>
        <stem>none</stem>
        <notations>
          <slur type="stop" number="1"/>
          </notations>
        </note>
      <note default-x="293.26" default-y="-25.00">
        <pitch>
          <step>D</step>
          <octave>4</octave>
          </pitch>
        <duration>1</duration>
        <voice>1</voice>
        <type>quarter</type>
        <stem>none</stem>
        </note>
      <note default-x="313.49" default-y="-25.00">
        <pitch>
          <step>D</step>
          <octave>4</octave>
          </pitch>
        <duration>1</duration>
        <voice>1</voice>
        <type>quarter</type>
        <stem>none</stem>
        <notations>
          <slur type="start" number="1"/>
          </notations>
        </note>
      <note default-x="333.73" default-y="-30.00">
        <pitch>
          <step>C</step>
          <octave>4</octave>
          </pitch>
        <duration>1</duration>
        <voice>1</voice>
        <type>quarter</type>
        <stem>none</stem>
        </note>
      <note default-x="353.97" default-y="-25.00">
        <pitch>
          <step>D</step>
          <octave>4</octave>
          </pitch>
        <duration>1</duration>
        <voice>1</voice>
        <type>quarter</type>
        <stem>none</stem>
        </note>
      <note default-x="374.20" default-y="-20.00">
        <pitch>
          <step>E</step>
          <octave>4</octave>
          </pitch>
        <duration>1</duration>
        <voice>1</voice>
        <type>quarter</type>
        <stem>none</stem>
        <notations>
          <slur type="stop" number="1"/>
          </notations>
        </note>
      <note default-x="394.44" default-y="-20.00">
        <pitch>
          <step>E</step>
          <octave>4</octave>
          </pitch>
        <duration>1</duration>
        <voice>1</voice>
        <type>quarter</type>
        <stem>none</stem>
        </note>
      <note default-x="414.67" default-y="-20.00">
        <pitch>
          <step>E</step>
          <octave>4</octave>
          </pitch>
        <duration>1</duration>
        <voice>1</voice>
        <type>quarter</type>
        <stem>none</stem>
        <notations>
          <slur type="start" number="1"/>
          </notations>
        </note>
      <note default-x="434.91" default-y="-10.00">
        <pitch>
          <step>G</step>
          <octave>4</octave>
          </pitch>
        <duration>1</duration>
        <voice>1</voice>
        <type>quarter</type>
        <stem>none</stem>
        <notations>
          <slur type="stop" number="1"/>
          </notations>
        </note>
      <note default-x="455.15" default-y="-5.00">
        <pitch>
          <step>A</step>
          <octave>4</octave>
          </pitch>
        <duration>1</duration>
        <voice>1</voice>
        <type>quarter</type>
        <stem>none</stem>
        </note>
      <note default-x="475.38" default-y="-5.00">
        <pitch>
          <step>A</step>
          <octave>4</octave>
          </pitch>
        <duration>1</duration>
        <voice>1</voice>
        <type>quarter</type>
        <stem>none</stem>
        <notations>
          <slur type="start" number="1"/>
          </notations>
        </note>
      <note default-x="495.62" default-y="-10.00">
        <pitch>
          <step>G</step>
          <octave>4</octave>
          </pitch>
        <duration>1</duration>
        <voice>1</voice>
        <type>quarter</type>
        <stem>none</stem>
        </note>
      <note default-x="515.85" default-y="-5.00">
        <pitch>
          <step>A</step>
          <octave>4</octave>
          </pitch>
        <duration>1</duration>
        <voice>1</voice>
        <type>quarter</type>
        <stem>none</stem>
        <notations>
          <slur type="stop" number="1"/>
          </notations>
        </note>
      <note default-x="536.09" default-y="-20.00">
        <pitch>
          <step>E</step>
          <octave>4</octave>
          </pitch>
        <duration>1</duration>
        <voice>1</voice>
        <type>quarter</type>
        <stem>none</stem>
        <notations>
          <slur type="start" number="1"/>
          </notations>
        </note>
      <note default-x="556.33" default-y="-25.00">
        <pitch>
          <step>D</step>
          <octave>4</octave>
          </pitch>
        <duration>1</duration>
        <voice>1</voice>
        <type>quarter</type>
        <stem>none</stem>
        </note>
      <note default-x="576.56" default-y="-15.00">
        <pitch>
          <step>F</step>
          <octave>4</octave>
          </pitch>
        <duration>1</duration>
        <voice>1</voice>
        <type>quarter</type>
        <stem>none</stem>
        </note>
      <note default-x="596.80" default-y="-20.00">
        <pitch>
          <step>E</step>
          <octave>4</octave>
          </pitch>
        <duration>1</duration>
        <voice>1</voice>
        <type>quarter</type>
        <stem>none</stem>
        </note>
      <note default-x="617.03" default-y="-25.00">
        <pitch>
          <step>D</step>
          <octave>4</octave>
          </pitch>
        <duration>1</duration>
        <voice>1</voice>
        <type>quarter</type>
        <stem>none</stem>
        <notations>
          <slur type="stop" number="1"/>
          </notations>
        </note>
      <note default-x="637.27" default-y="-25.00">
        <pitch>
          <step>D</step>
          <octave>4</octave>
          </pitch>
        <duration>1</duration>
        <voice>1</voice>
        <type>quarter</type>
        <stem>none</stem>
        <notations>
          <slur type="start" number="1"/>
          </notations>
        </note>
      <note default-x="657.51" default-y="-30.00">
        <pitch>
          <step>C</step>
          <octave>4</octave>
          </pitch>
        <duration>1</duration>
        <voice>1</voice>
        <type>quarter</type>
        <stem>none</stem>
        </note>
      <note default-x="677.74" default-y="-25.00">
        <pitch>
          <step>D</step>
          <octave>4</octave>
          </pitch>
        <duration>1</duration>
        <voice>1</voice>
        <type>quarter</type>
        <stem>none</stem>
        </note>
      <note default-x="697.98" default-y="-20.00">
        <pitch>
          <step>E</step>
          <octave>4</octave>
          </pitch>
        <duration>1</duration>
        <voice>1</voice>
        <type>quarter</type>
        <stem>none</stem>
        <notations>
          <slur type="stop" number="1"/>
          </notations>
        </note>
      <note default-x="718.21" default-y="-20.00">
        <pitch>
          <step>E</step>
          <octave>4</octave>
          </pitch>
        <duration>1</duration>
        <voice>1</voice>
        <type>quarter</type>
        <stem>none</stem>
        <notations>
          <slur type="start" number="1"/>
          </notations>
        </note>
      <note default-x="738.45" default-y="-25.00">
        <pitch>
          <step>D</step>
          <octave>4</octave>
          </pitch>
        <duration>1</duration>
        <voice>1</voice>
        <type>quarter</type>
        <stem>none</stem>
        </note>
      <note default-x="758.69" default-y="-30.00">
        <pitch>
          <step>C</step>
          <octave>4</octave>
          </pitch>
        <duration>1</duration>
        <voice>1</voice>
        <type>quarter</type>
        <stem>none</stem>
        <notations>
          <slur type="stop" number="1"/>
          </notations>
        </note>
      <note default-x="778.92" default-y="-25.00">
        <pitch>
          <step>D</step>
          <octave>4</octave>
          </pitch>
        <duration>1</duration>
        <voice>1</voice>
        <type>quarter</type>
        <stem>none</stem>
        <notations>
          <slur type="start" number="1"/>
          </notations>
        </note>
      <note default-x="799.16" default-y="-30.00">
        <pitch>
          <step>C</step>
          <octave>4</octave>
          </pitch>
        <duration>1</duration>
        <voice>1</voice>
        <type>quarter</type>
        <stem>none</stem>
        </note>
      <note default-x="819.39" default-y="-35.00">
        <pitch>
          <step>B</step>
          <octave>3</octave>
          </pitch>
        <duration>1</duration>
        <voice>1</voice>
        <type>quarter</type>
        <stem>none</stem>
        </note>
      <note default-x="839.63" default-y="-40.00">
        <pitch>
          <step>A</step>
          <octave>3</octave>
          </pitch>
        <duration>1</duration>
        <voice>1</voice>
        <type>quarter</type>
        <stem>none</stem>
        <notations>
          <slur type="stop" number="1"/>
          </notations>
        </note>
      <note default-x="859.87" default-y="-30.00">
        <pitch>
          <step>C</step>
          <octave>4</octave>
          </pitch>
        <duration>1</duration>
        <voice>1</voice>
        <type>quarter</type>
        <stem>none</stem>
        <notations>
          <slur type="start" number="1"/>
          </notations>
        </note>
      <note default-x="880.10" default-y="-40.00">
        <pitch>
          <step>A</step>
          <octave>3</octave>
          </pitch>
        <duration>1</duration>
        <voice>1</voice>
        <type>quarter</type>
        <stem>none</stem>
        </note>
      <note default-x="900.34" default-y="-45.00">
        <pitch>
          <step>G</step>
          <octave>3</octave>
          </pitch>
        <duration>1</duration>
        <voice>1</voice>
        <type>quarter</type>
        <stem>none</stem>
        </note>
      <note default-x="920.57" default-y="-40.00">
        <pitch>
          <step>A</step>
          <octave>3</octave>
          </pitch>
        <duration>1</duration>
        <voice>1</voice>
        <type>quarter</type>
        <stem>none</stem>
        </note>
      <note default-x="940.81" default-y="-45.00">
        <pitch>
          <step>G</step>
          <octave>3</octave>
          </pitch>
        <duration>1</duration>
        <voice>1</voice>
        <type>quarter</type>
        <stem>none</stem>
        <notations>
          <slur type="stop" number="1"/>
          </notations>
        </note>
      <note default-x="961.05" default-y="-40.00">
        <pitch>
          <step>A</step>
          <octave>3</octave>
          </pitch>
        <duration>1</duration>
        <voice>1</voice>
        <type>quarter</type>
        <stem>none</stem>
        <lyric number="1">
          <syllabic>begin</syllabic>
          <text>e</text>
          </lyric>
        </note>
      <note default-x="981.28" default-y="-30.00">
        <pitch>
          <step>C</step>
          <octave>4</octave>
          </pitch>
        <duration>1</duration>
        <voice>1</voice>
        <type>quarter</type>
        <stem>none</stem>
        <lyric number="1">
          <syllabic>middle</syllabic>
          <text>le</text>
          </lyric>
        </note>
      <note default-x="1001.52" default-y="-25.00">
        <pitch>
          <step>D</step>
          <octave>4</octave>
          </pitch>
        <duration>1</duration>
        <voice>1</voice>
        <type>quarter</type>
        <stem>none</stem>
        <lyric number="1">
          <syllabic>middle</syllabic>
          <text>i</text>
          </lyric>
        </note>
      <note default-x="1026.40" default-y="-35.00">
        <pitch>
          <step>B</step>
          <octave>3</octave>
          </pitch>
        <duration>1</duration>
        <voice>1</voice>
        <type>quarter</type>
        <stem>none</stem>
        <notations>
          <slur type="start" number="1"/>
          </notations>
        <lyric number="1">
          <syllabic>end</syllabic>
          <text>son.</text>
          </lyric>
        </note>
      <note default-x="1054.78" default-y="-40.00">
        <pitch>
          <step>A</step>
          <octave>3</octave>
          </pitch>
        <duration>1</duration>
        <voice>1</voice>
        <type>quarter</type>
        <stem>none</stem>
        <notations>
          <slur type="stop" number="1"/>
          <articulations>
            <caesura/>
            </articulations>
          </notations>
        </note>
      <barline location="right">
        <bar-style>light-heavy</bar-style>
        </barline>
      </measure>
    </part>
  </score-partwise>
